{
"meta":{"test_sets":[],"test_metrics":[],"learn_metrics":[{"best_value":"Min","name":"RMSE"}],"launch_mode":"Train","parameters":"","iteration_count":1000,"learn_sets":["learn"],"name":"experiment"},
"iterations":[
{"learn":[14.59871775],"iteration":0,"passed_time":0.1437067001,"remaining_time":143.5629934},
{"learn":[14.22518863],"iteration":1,"passed_time":0.1445004299,"remaining_time":72.10571454},
{"learn":[13.8866124],"iteration":2,"passed_time":0.1453556659,"remaining_time":48.30653298},
{"learn":[13.52356875],"iteration":3,"passed_time":0.1473027283,"remaining_time":36.67837935},
{"learn":[13.18870211],"iteration":4,"passed_time":0.1483689168,"remaining_time":29.52541445},
{"learn":[12.9124226],"iteration":5,"passed_time":0.1501063517,"remaining_time":24.86761894},
{"learn":[12.60003351],"iteration":6,"passed_time":0.1509557021,"remaining_time":21.4141446},
{"learn":[12.32990573],"iteration":7,"passed_time":0.1529382158,"remaining_time":18.96433876},
{"learn":[12.0660619],"iteration":8,"passed_time":0.1553980576,"remaining_time":17.11105278},
{"learn":[11.77309809],"iteration":9,"passed_time":0.1572743209,"remaining_time":15.57015776},
{"learn":[11.49227636],"iteration":10,"passed_time":0.1591084706,"remaining_time":14.30529795},
{"learn":[11.26264833],"iteration":11,"passed_time":0.1611253018,"remaining_time":13.26598318},
{"learn":[11.04260393],"iteration":12,"passed_time":0.1618940865,"remaining_time":12.29149718},
{"learn":[10.79916926],"iteration":13,"passed_time":0.1627970545,"remaining_time":11.46556398},
{"learn":[10.5541002],"iteration":14,"passed_time":0.1642018243,"remaining_time":10.78258646},
{"learn":[10.31918115],"iteration":15,"passed_time":0.1646746257,"remaining_time":10.12748948},
{"learn":[10.10004441],"iteration":16,"passed_time":0.167003484,"remaining_time":9.656730868},
{"learn":[9.894556723],"iteration":17,"passed_time":0.1687340886,"remaining_time":9.205381946},
{"learn":[9.690174082],"iteration":18,"passed_time":0.1701848789,"remaining_time":8.786914013},
{"learn":[9.506034866],"iteration":19,"passed_time":0.1715870728,"remaining_time":8.407766567},
{"learn":[9.338524633],"iteration":20,"passed_time":0.1727787329,"remaining_time":8.054779978},
{"learn":[9.170203312],"iteration":21,"passed_time":0.1744866651,"remaining_time":7.756725385},
{"learn":[9.010299969],"iteration":22,"passed_time":0.1755672892,"remaining_time":7.457793111},
{"learn":[8.843866678],"iteration":23,"passed_time":0.1766768034,"remaining_time":7.184856672},
{"learn":[8.690548059],"iteration":24,"passed_time":0.1778151735,"remaining_time":6.934791765},
{"learn":[8.555307687],"iteration":25,"passed_time":0.17855875,"remaining_time":6.689085481},
{"learn":[8.413851302],"iteration":26,"passed_time":0.1794407045,"remaining_time":6.466511312},
{"learn":[8.29256019],"iteration":27,"passed_time":0.1803826593,"remaining_time":6.261855171},
{"learn":[8.162193833],"iteration":28,"passed_time":0.1814649676,"remaining_time":6.075947709},
{"learn":[8.040736294],"iteration":29,"passed_time":0.1821604038,"remaining_time":5.889853056},
{"learn":[7.921220278],"iteration":30,"passed_time":0.1833005099,"remaining_time":5.729619164},
{"learn":[7.809589039],"iteration":31,"passed_time":0.1841061098,"remaining_time":5.569209821},
{"learn":[7.699675801],"iteration":32,"passed_time":0.1850469437,"remaining_time":5.4224362},
{"learn":[7.60645267],"iteration":33,"passed_time":0.1859593906,"remaining_time":5.28343445},
{"learn":[7.498880302],"iteration":34,"passed_time":0.1870031351,"remaining_time":5.155943581},
{"learn":[7.401158744],"iteration":35,"passed_time":0.1878135802,"remaining_time":5.029230315},
{"learn":[7.306431077],"iteration":36,"passed_time":0.1885422204,"remaining_time":4.907193466},
{"learn":[7.223863468],"iteration":37,"passed_time":0.1893704905,"remaining_time":4.794063471},
{"learn":[7.143477682],"iteration":38,"passed_time":0.1901133882,"remaining_time":4.684588872},
{"learn":[7.062817131],"iteration":39,"passed_time":0.1909891589,"remaining_time":4.583739813},
{"learn":[6.990793435],"iteration":40,"passed_time":0.1915893621,"remaining_time":4.481321908},
{"learn":[6.931862224],"iteration":41,"passed_time":0.1925036076,"remaining_time":4.390915621},
{"learn":[6.858296558],"iteration":42,"passed_time":0.1934538079,"remaining_time":4.305471957},
{"learn":[6.786268161],"iteration":43,"passed_time":0.1941385866,"remaining_time":4.218102017},
{"learn":[6.717118549],"iteration":44,"passed_time":0.1950399444,"remaining_time":4.139181043},
{"learn":[6.652948106],"iteration":45,"passed_time":0.1960109071,"remaining_time":4.065095769},
{"learn":[6.589686076],"iteration":46,"passed_time":0.1967483927,"remaining_time":3.989387622},
{"learn":[6.531283097],"iteration":47,"passed_time":0.1974575937,"remaining_time":3.916242275},
{"learn":[6.471368031],"iteration":48,"passed_time":0.1984125606,"remaining_time":3.85082337},
{"learn":[6.416481395],"iteration":49,"passed_time":0.1994638847,"remaining_time":3.789813809},
{"learn":[6.369870822],"iteration":50,"passed_time":0.2003003709,"remaining_time":3.727157881},
{"learn":[6.325678067],"iteration":51,"passed_time":0.2010948497,"remaining_time":3.666113798},
{"learn":[6.275766122],"iteration":52,"passed_time":0.2019211963,"remaining_time":3.607912697},
{"learn":[6.224773967],"iteration":53,"passed_time":0.2027537226,"remaining_time":3.551944844},
{"learn":[6.182249254],"iteration":54,"passed_time":0.2038676491,"remaining_time":3.50281688},
{"learn":[6.139904173],"iteration":55,"passed_time":0.204829169,"remaining_time":3.452834563},
{"learn":[6.100525536],"iteration":56,"passed_time":0.2055348852,"remaining_time":3.400340294},
{"learn":[6.062568564],"iteration":57,"passed_time":0.2062756626,"remaining_time":3.350201278},
{"learn":[6.030559288],"iteration":58,"passed_time":0.2071726242,"remaining_time":3.304227786},
{"learn":[5.997931376],"iteration":59,"passed_time":0.2078319662,"remaining_time":3.256034138},
{"learn":[5.964103835],"iteration":60,"passed_time":0.2088586142,"remaining_time":3.215053095},
{"learn":[5.933729724],"iteration":61,"passed_time":0.2101951159,"remaining_time":3.180048688},
{"learn":[5.901932711],"iteration":62,"passed_time":0.2110037806,"remaining_time":3.138262578},
{"learn":[5.873727795],"iteration":63,"passed_time":0.211853052,"remaining_time":3.098350885},
{"learn":[5.846485734],"iteration":64,"passed_time":0.21275193,"remaining_time":3.060354686},
{"learn":[5.820630862],"iteration":65,"passed_time":0.2136411056,"remaining_time":3.023345343},
{"learn":[5.793646238],"iteration":66,"passed_time":0.2146958064,"remaining_time":2.989719215},
{"learn":[5.765388646],"iteration":67,"passed_time":0.2155745097,"remaining_time":2.954638868},
{"learn":[5.747073912],"iteration":68,"passed_time":0.216406331,"remaining_time":2.919917306},
{"learn":[5.722315217],"iteration":69,"passed_time":0.2170434831,"remaining_time":2.883577704},
{"learn":[5.699970599],"iteration":70,"passed_time":0.2179773251,"remaining_time":2.852125845},
{"learn":[5.682732647],"iteration":71,"passed_time":0.2187997401,"remaining_time":2.820085539},
{"learn":[5.663525791],"iteration":72,"passed_time":0.2196139443,"remaining_time":2.788796252},
{"learn":[5.642381613],"iteration":73,"passed_time":0.2203223047,"remaining_time":2.757006137},
{"learn":[5.621404779],"iteration":74,"passed_time":0.2212169657,"remaining_time":2.728342577},
{"learn":[5.602460129],"iteration":75,"passed_time":0.2222413295,"remaining_time":2.70198669},
{"learn":[5.587337574],"iteration":76,"passed_time":0.2231989081,"remaining_time":2.675488211},
{"learn":[5.572393026],"iteration":77,"passed_time":0.2241203103,"remaining_time":2.649217002},
{"learn":[5.558425806],"iteration":78,"passed_time":0.2248986053,"remaining_time":2.621919183},
{"learn":[5.541518902],"iteration":79,"passed_time":0.2256566144,"remaining_time":2.595051065},
{"learn":[5.526157283],"iteration":80,"passed_time":0.2263682024,"remaining_time":2.568300963},
{"learn":[5.511746977],"iteration":81,"passed_time":0.2270343859,"remaining_time":2.541677637},
{"learn":[5.504975022],"iteration":82,"passed_time":0.2275812528,"remaining_time":2.514361552},
{"learn":[5.493980522],"iteration":83,"passed_time":0.2283905507,"remaining_time":2.490544576},
{"learn":[5.480745463],"iteration":84,"passed_time":0.2292930067,"remaining_time":2.468271778},
{"learn":[5.464052013],"iteration":85,"passed_time":0.2303388632,"remaining_time":2.448020011},
{"learn":[5.449143727],"iteration":86,"passed_time":0.2311340057,"remaining_time":2.425578703},
{"learn":[5.438255432],"iteration":87,"passed_time":0.2319562128,"remaining_time":2.403909842},
{"learn":[5.425927931],"iteration":88,"passed_time":0.2328911533,"remaining_time":2.383863378},
{"learn":[5.412331217],"iteration":89,"passed_time":0.2336091237,"remaining_time":2.362047806},
{"learn":[5.400691499],"iteration":90,"passed_time":0.2344513941,"remaining_time":2.341937552},
{"learn":[5.391618744],"iteration":91,"passed_time":0.2353036674,"remaining_time":2.322344891},
{"learn":[5.380766572],"iteration":92,"passed_time":0.2360060687,"remaining_time":2.301693594},
{"learn":[5.372207183],"iteration":93,"passed_time":0.2369539795,"remaining_time":2.283833037},
{"learn":[5.362918837],"iteration":94,"passed_time":0.2381014946,"remaining_time":2.268230027},
{"learn":[5.348292324],"iteration":95,"passed_time":0.2389855007,"remaining_time":2.250446798},
{"learn":[5.339772295],"iteration":96,"passed_time":0.2400630395,"remaining_time":2.234813656},
{"learn":[5.331515983],"iteration":97,"passed_time":0.2408720388,"remaining_time":2.217005908},
{"learn":[5.323861644],"iteration":98,"passed_time":0.2415168805,"remaining_time":2.198047569},
{"learn":[5.313277281],"iteration":99,"passed_time":0.2422969878,"remaining_time":2.180672891},
{"learn":[5.30685627],"iteration":100,"passed_time":0.2432456298,"remaining_time":2.165126943},
{"learn":[5.29652059],"iteration":101,"passed_time":0.2447598691,"remaining_time":2.154846691},
{"learn":[5.288350766],"iteration":102,"passed_time":0.2453624765,"remaining_time":2.13679749},
{"learn":[5.27993346],"iteration":103,"passed_time":0.24610658,"remaining_time":2.120302843},
{"learn":[5.271789139],"iteration":104,"passed_time":0.247150004,"remaining_time":2.106659558},
{"learn":[5.262684686],"iteration":105,"passed_time":0.2481115709,"remaining_time":2.092563626},
{"learn":[5.251619772],"iteration":106,"passed_time":0.2488557123,"remaining_time":2.076898609},
{"learn":[5.241012171],"iteration":107,"passed_time":0.2497454972,"remaining_time":2.06271281},
{"learn":[5.232684032],"iteration":108,"passed_time":0.2505603736,"remaining_time":2.04815865},
{"learn":[5.224267141],"iteration":109,"passed_time":0.2514704875,"remaining_time":2.034624853},
{"learn":[5.216324968],"iteration":110,"passed_time":0.2524352068,"remaining_time":2.021755845},
{"learn":[5.211102527],"iteration":111,"passed_time":0.2532279924,"remaining_time":2.007736225},
{"learn":[5.206364257],"iteration":112,"passed_time":0.2542012456,"remaining_time":1.995367299},
{"learn":[5.196937641],"iteration":113,"passed_time":0.2550979441,"remaining_time":1.98260332},
{"learn":[5.190746047],"iteration":114,"passed_time":0.2558216411,"remaining_time":1.968714368},
{"learn":[5.181885213],"iteration":115,"passed_time":0.2567651788,"remaining_time":1.956727742},
{"learn":[5.178293568],"iteration":116,"passed_time":0.2575092546,"remaining_time":1.943424546},
{"learn":[5.170991438],"iteration":117,"passed_time":0.2582882233,"remaining_time":1.930595025},
{"learn":[5.166257212],"iteration":118,"passed_time":0.2592425038,"remaining_time":1.919265932},
{"learn":[5.161421246],"iteration":119,"passed_time":0.2599947626,"remaining_time":1.906628259},
{"learn":[5.158223542],"iteration":120,"passed_time":0.2611697503,"remaining_time":1.897257938},
{"learn":[5.15470988],"iteration":121,"passed_time":0.2619610905,"remaining_time":1.885260963},
{"learn":[5.146388143],"iteration":122,"passed_time":0.2631285548,"remaining_time":1.876127989},
{"learn":[5.139529364],"iteration":123,"passed_time":0.2641205787,"remaining_time":1.865884089},
{"learn":[5.134276023],"iteration":124,"passed_time":0.265270783,"remaining_time":1.856895481},
{"learn":[5.128536065],"iteration":125,"passed_time":0.2660600757,"remaining_time":1.845527827},
{"learn":[5.123300353],"iteration":126,"passed_time":0.2666431366,"remaining_time":1.83290912},
{"learn":[5.116200518],"iteration":127,"passed_time":0.2675101591,"remaining_time":1.822412959},
{"learn":[5.108728704],"iteration":128,"passed_time":0.2683923975,"remaining_time":1.812168824},
{"learn":[5.104075866],"iteration":129,"passed_time":0.2691040005,"remaining_time":1.800926772},
{"learn":[5.100317606],"iteration":130,"passed_time":0.2702049901,"remaining_time":1.792428522},
{"learn":[5.095814182],"iteration":131,"passed_time":0.2711708511,"remaining_time":1.783153779},
{"learn":[5.092146915],"iteration":132,"passed_time":0.271960307,"remaining_time":1.772854031},
{"learn":[5.085258329],"iteration":133,"passed_time":0.272791709,"remaining_time":1.762967313},
{"learn":[5.079219421],"iteration":134,"passed_time":0.2734272764,"remaining_time":1.751959956},
{"learn":[5.076476829],"iteration":135,"passed_time":0.2741426846,"remaining_time":1.741612349},
{"learn":[5.072133867],"iteration":136,"passed_time":0.2747672855,"remaining_time":1.730833339},
{"learn":[5.067031564],"iteration":137,"passed_time":0.2755375645,"remaining_time":1.721111454},
{"learn":[5.061358312],"iteration":138,"passed_time":0.2762505722,"remaining_time":1.711163617},
{"learn":[5.056759124],"iteration":139,"passed_time":0.2770858776,"remaining_time":1.702098962},
{"learn":[5.050254],"iteration":140,"passed_time":0.2780808743,"remaining_time":1.694123908},
{"learn":[5.048376474],"iteration":141,"passed_time":0.2788665759,"remaining_time":1.68498255},
{"learn":[5.042603751],"iteration":142,"passed_time":0.2796126848,"remaining_time":1.675720775},
{"learn":[5.037477349],"iteration":143,"passed_time":0.2807988483,"remaining_time":1.669193154},
{"learn":[5.03230489],"iteration":144,"passed_time":0.2815801742,"remaining_time":1.660352062},
{"learn":[5.025976187],"iteration":145,"passed_time":0.2828425686,"remaining_time":1.654435298},
{"learn":[5.01952451],"iteration":146,"passed_time":0.2838647294,"remaining_time":1.647187852},
{"learn":[5.017569424],"iteration":147,"passed_time":0.2848679616,"remaining_time":1.639915562},
{"learn":[5.008962367],"iteration":148,"passed_time":0.2855166949,"remaining_time":1.630702734},
{"learn":[5.003880266],"iteration":149,"passed_time":0.2863361248,"remaining_time":1.622571374},
{"learn":[4.996387564],"iteration":150,"passed_time":0.2873624967,"remaining_time":1.615700396},
{"learn":[4.993361683],"iteration":151,"passed_time":0.2884871746,"remaining_time":1.609454764},
{"learn":[4.99005752],"iteration":152,"passed_time":0.289432742,"remaining_time":1.602284526},
{"learn":[4.986908764],"iteration":153,"passed_time":0.2903146462,"remaining_time":1.594845394},
{"learn":[4.985207175],"iteration":154,"passed_time":0.2912896522,"remaining_time":1.587998427},
{"learn":[4.979003494],"iteration":155,"passed_time":0.2925478191,"remaining_time":1.582758714},
{"learn":[4.973142217],"iteration":156,"passed_time":0.2938578441,"remaining_time":1.577848169},
{"learn":[4.967056696],"iteration":157,"passed_time":0.2947202469,"remaining_time":1.570597771},
{"learn":[4.961460696],"iteration":158,"passed_time":0.2956585924,"remaining_time":1.56382941},
{"learn":[4.954240363],"iteration":159,"passed_time":0.2965989896,"remaining_time":1.557144696},
{"learn":[4.952320707],"iteration":160,"passed_time":0.2971512976,"remaining_time":1.548508936},
{"learn":[4.948337777],"iteration":161,"passed_time":0.2981206666,"remaining_time":1.542130362},
{"learn":[4.943228639],"iteration":162,"passed_time":0.2990584852,"remaining_time":1.535656148},
{"learn":[4.938545759],"iteration":163,"passed_time":0.2996971584,"remaining_time":1.527724539},
{"learn":[4.935330572],"iteration":164,"passed_time":0.3006344517,"remaining_time":1.521392528},
{"learn":[4.932051543],"iteration":165,"passed_time":0.3014745542,"remaining_time":1.514637218},
{"learn":[4.928964153],"iteration":166,"passed_time":0.3021983696,"remaining_time":1.507372706},
{"learn":[4.922860227],"iteration":167,"passed_time":0.3031889857,"remaining_time":1.501507358},
{"learn":[4.917668772],"iteration":168,"passed_time":0.3041152421,"remaining_time":1.495383232},
{"learn":[4.910365386],"iteration":169,"passed_time":0.3050223548,"remaining_time":1.489226791},
{"learn":[4.906457206],"iteration":170,"passed_time":0.3058063819,"remaining_time":1.482535033},
{"learn":[4.901996508],"iteration":171,"passed_time":0.3066991764,"remaining_time":1.47643557},
{"learn":[4.896816173],"iteration":172,"passed_time":0.30759127,"remaining_time":1.47039295},
{"learn":[4.891123132],"iteration":173,"passed_time":0.3084419231,"remaining_time":1.464212807},
{"learn":[4.887630202],"iteration":174,"passed_time":0.3093874383,"remaining_time":1.458540781},
{"learn":[4.885259712],"iteration":175,"passed_time":0.3103214055,"remaining_time":1.452868398},
{"learn":[4.880659728],"iteration":176,"passed_time":0.3113888572,"remaining_time":1.447870223},
{"learn":[4.877299723],"iteration":177,"passed_time":0.312128434,"remaining_time":1.441402094},
{"learn":[4.874038772],"iteration":178,"passed_time":0.3127806619,"remaining_time":1.434597337},
{"learn":[4.86943698],"iteration":179,"passed_time":0.3137975638,"remaining_time":1.429522235},
{"learn":[4.861268711],"iteration":180,"passed_time":0.314713475,"remaining_time":1.424035006},
{"learn":[4.858673056],"iteration":181,"passed_time":0.3155228172,"remaining_time":1.418119035},
{"learn":[4.854036207],"iteration":182,"passed_time":0.3161660304,"remaining_time":1.411517196},
{"learn":[4.85130244],"iteration":183,"passed_time":0.3175529201,"remaining_time":1.408278168},
{"learn":[4.847510084],"iteration":184,"passed_time":0.3183207562,"remaining_time":1.40233198},
{"learn":[4.845691673],"iteration":185,"passed_time":0.3191698543,"remaining_time":1.396797104},
{"learn":[4.842058646],"iteration":186,"passed_time":0.3203018069,"remaining_time":1.39254208},
{"learn":[4.838623675],"iteration":187,"passed_time":0.3213854944,"remaining_time":1.388111816},
{"learn":[4.834602161],"iteration":188,"passed_time":0.3223863153,"remaining_time":1.383361385},
{"learn":[4.830858976],"iteration":189,"passed_time":0.3234878325,"remaining_time":1.379079707},
{"learn":[4.827590511],"iteration":190,"passed_time":0.3243886389,"remaining_time":1.373981198},
{"learn":[4.822246226],"iteration":191,"passed_time":0.3249582622,"remaining_time":1.367532687},
{"learn":[4.816686395],"iteration":192,"passed_time":0.3257713768,"remaining_time":1.362163218},
{"learn":[4.814797121],"iteration":193,"passed_time":0.3264835588,"remaining_time":1.356421384},
{"learn":[4.811639392],"iteration":194,"passed_time":0.3274466199,"remaining_time":1.351766816},
{"learn":[4.804813432],"iteration":195,"passed_time":0.3282864124,"remaining_time":1.346644263},
{"learn":[4.80251613],"iteration":196,"passed_time":0.3289039629,"remaining_time":1.340659301},
{"learn":[4.800087884],"iteration":197,"passed_time":0.3298875457,"remaining_time":1.33621117},
{"learn":[4.794773135],"iteration":198,"passed_time":0.3307744393,"remaining_time":1.331408673},
{"learn":[4.791664833],"iteration":199,"passed_time":0.3317353094,"remaining_time":1.326941237},
{"learn":[4.785989873],"iteration":200,"passed_time":0.3325924983,"remaining_time":1.322096548},
{"learn":[4.782387142],"iteration":201,"passed_time":0.3334570198,"remaining_time":1.317320306},
{"learn":[4.778623704],"iteration":202,"passed_time":0.3344485541,"remaining_time":1.313081269},
{"learn":[4.775772178],"iteration":203,"passed_time":0.3353239697,"remaining_time":1.30842098},
{"learn":[4.77023101],"iteration":204,"passed_time":0.3364295564,"remaining_time":1.304690231},
{"learn":[4.764496689],"iteration":205,"passed_time":0.3373321391,"remaining_time":1.300202517},
{"learn":[4.763138716],"iteration":206,"passed_time":0.3381545016,"remaining_time":1.295442124},
{"learn":[4.758053283],"iteration":207,"passed_time":0.3391499715,"remaining_time":1.291378738},
{"learn":[4.755063788],"iteration":208,"passed_time":0.3400884672,"remaining_time":1.287129079},
{"learn":[4.752465267],"iteration":209,"passed_time":0.3410056651,"remaining_time":1.282830835},
{"learn":[4.748067377],"iteration":210,"passed_time":0.3416771235,"remaining_time":1.277645737},
{"learn":[4.744163298],"iteration":211,"passed_time":0.3426462457,"remaining_time":1.27360963},
{"learn":[4.736670896],"iteration":212,"passed_time":0.3432777988,"remaining_time":1.268355059},
{"learn":[4.73349255],"iteration":213,"passed_time":0.3442074383,"remaining_time":1.264238535},
{"learn":[4.731864595],"iteration":214,"passed_time":0.3449760777,"remaining_time":1.259563819},
{"learn":[4.728398311],"iteration":215,"passed_time":0.3458593386,"remaining_time":1.255341303},
{"learn":[4.723865975],"iteration":216,"passed_time":0.346685086,"remaining_time":1.250942038},
{"learn":[4.723483365],"iteration":217,"passed_time":0.3475712135,"remaining_time":1.246792151},
{"learn":[4.72095416],"iteration":218,"passed_time":0.3485900926,"remaining_time":1.24314549},
{"learn":[4.716173382],"iteration":219,"passed_time":0.3494320493,"remaining_time":1.238895448},
{"learn":[4.710563974],"iteration":220,"passed_time":0.3502387175,"remaining_time":1.234551859},
{"learn":[4.707160263],"iteration":221,"passed_time":0.3513868049,"remaining_time":1.231436641},
{"learn":[4.70408351],"iteration":222,"passed_time":0.352307125,"remaining_time":1.227545454},
{"learn":[4.702501831],"iteration":223,"passed_time":0.3533010184,"remaining_time":1.223935671},
{"learn":[4.700269738],"iteration":224,"passed_time":0.3540340556,"remaining_time":1.219450636},
{"learn":[4.695346302],"iteration":225,"passed_time":0.3546796641,"remaining_time":1.214699381},
{"learn":[4.689769299],"iteration":226,"passed_time":0.3553969313,"remaining_time":1.210228317},
{"learn":[4.687919514],"iteration":227,"passed_time":0.3562456631,"remaining_time":1.206235315},
{"learn":[4.682982074],"iteration":228,"passed_time":0.356973482,"remaining_time":1.201862684},
{"learn":[4.679578702],"iteration":229,"passed_time":0.3580085581,"remaining_time":1.19855039},
{"learn":[4.675751423],"iteration":230,"passed_time":0.3589180202,"remaining_time":1.194839643},
{"learn":[4.672710726],"iteration":231,"passed_time":0.3596231447,"remaining_time":1.190476617},
{"learn":[4.6690533],"iteration":232,"passed_time":0.3604396264,"remaining_time":1.18651156},
{"learn":[4.667595702],"iteration":233,"passed_time":0.3612139133,"remaining_time":1.182435289},
{"learn":[4.664241291],"iteration":234,"passed_time":0.3618433096,"remaining_time":1.177915455},
{"learn":[4.662246999],"iteration":235,"passed_time":0.3627374378,"remaining_time":1.174285604},
{"learn":[4.658668443],"iteration":236,"passed_time":0.3634760085,"remaining_time":1.170178036},
{"learn":[4.658017572],"iteration":237,"passed_time":0.3643150378,"remaining_time":1.166420415},
{"learn":[4.657656705],"iteration":238,"passed_time":0.3652441001,"remaining_time":1.162973892},
{"learn":[4.653242871],"iteration":239,"passed_time":0.3661120539,"remaining_time":1.159354837},
{"learn":[4.6507302],"iteration":240,"passed_time":0.3670686708,"remaining_time":1.156037847},
{"learn":[4.647671336],"iteration":241,"passed_time":0.3681487627,"remaining_time":1.153127116},
{"learn":[4.645506007],"iteration":242,"passed_time":0.3691199762,"remaining_time":1.149892272},
{"learn":[4.641297906],"iteration":243,"passed_time":0.3701415144,"remaining_time":1.146831905},
{"learn":[4.63798107],"iteration":244,"passed_time":0.3708640912,"remaining_time":1.142866893},
{"learn":[4.635062318],"iteration":245,"passed_time":0.3716330227,"remaining_time":1.139070322},
{"learn":[4.631606017],"iteration":246,"passed_time":0.3725425337,"remaining_time":1.135726833},
{"learn":[4.630215494],"iteration":247,"passed_time":0.3732632022,"remaining_time":1.131830355},
{"learn":[4.62729814],"iteration":248,"passed_time":0.3741709268,"remaining_time":1.128523558},
{"learn":[4.624691756],"iteration":249,"passed_time":0.3751317209,"remaining_time":1.125395163},
{"learn":[4.621840053],"iteration":250,"passed_time":0.3760030323,"remaining_time":1.122017017},
{"learn":[4.619602091],"iteration":251,"passed_time":0.3770078582,"remaining_time":1.119055071},
{"learn":[4.613584029],"iteration":252,"passed_time":0.377882906,"remaining_time":1.115725418},
{"learn":[4.6119388],"iteration":253,"passed_time":0.3786252481,"remaining_time":1.112025335},
{"learn":[4.60870702],"iteration":254,"passed_time":0.3794343208,"remaining_time":1.108543408},
{"learn":[4.604771557],"iteration":255,"passed_time":0.3802131903,"remaining_time":1.104994584},
{"learn":[4.604231277],"iteration":256,"passed_time":0.3809653485,"remaining_time":1.101390093},
{"learn":[4.600750354],"iteration":257,"passed_time":0.3815355217,"remaining_time":1.09728433},
{"learn":[4.596488253],"iteration":258,"passed_time":0.3824252365,"remaining_time":1.094120078},
{"learn":[4.59470784],"iteration":259,"passed_time":0.3831351265,"remaining_time":1.090461514},
{"learn":[4.588818005],"iteration":260,"passed_time":0.3841583362,"remaining_time":1.087712684},
{"learn":[4.585054174],"iteration":261,"passed_time":0.3853188798,"remaining_time":1.085363868},
{"learn":[4.581471435],"iteration":262,"passed_time":0.3866236374,"remaining_time":1.083428216},
{"learn":[4.577555199],"iteration":263,"passed_time":0.3875373378,"remaining_time":1.080407123},
{"learn":[4.57457145],"iteration":264,"passed_time":0.3883598523,"remaining_time":1.077149024},
{"learn":[4.573029224],"iteration":265,"passed_time":0.3890555672,"remaining_time":1.073559347},
{"learn":[4.571326203],"iteration":266,"passed_time":0.3900765989,"remaining_time":1.070884446},
{"learn":[4.571019224],"iteration":267,"passed_time":0.391338921,"remaining_time":1.068880934},
{"learn":[4.565766631],"iteration":268,"passed_time":0.3929241342,"remaining_time":1.06776038},
{"learn":[4.563383471],"iteration":269,"passed_time":0.393944509,"remaining_time":1.065109228},
{"learn":[4.558165805],"iteration":270,"passed_time":0.3947969063,"remaining_time":1.062018246},
{"learn":[4.55629209],"iteration":271,"passed_time":0.395845489,"remaining_time":1.059468809},
{"learn":[4.549383848],"iteration":272,"passed_time":0.3966755276,"remaining_time":1.056348383},
{"learn":[4.546227503],"iteration":273,"passed_time":0.3975214696,"remaining_time":1.053286814},
{"learn":[4.540620977],"iteration":274,"passed_time":0.3984666562,"remaining_time":1.050503003},
{"learn":[4.532898237],"iteration":275,"passed_time":0.3991929875,"remaining_time":1.047158417},
{"learn":[4.529757367],"iteration":276,"passed_time":0.4000686431,"remaining_time":1.044222487},
{"learn":[4.52579294],"iteration":277,"passed_time":0.4007493203,"remaining_time":1.040794997},
{"learn":[4.521572155],"iteration":278,"passed_time":0.401872852,"remaining_time":1.038531635},
{"learn":[4.518818099],"iteration":279,"passed_time":0.4028642595,"remaining_time":1.035936667},
{"learn":[4.514012334],"iteration":280,"passed_time":0.4040528671,"remaining_time":1.033857692},
{"learn":[4.508331416],"iteration":281,"passed_time":0.4049467736,"remaining_time":1.031034693},
{"learn":[4.506038537],"iteration":282,"passed_time":0.4056586754,"remaining_time":1.027764206},
{"learn":[4.505805643],"iteration":283,"passed_time":0.4066153854,"remaining_time":1.025128929},
{"learn":[4.501550352],"iteration":284,"passed_time":0.4076996639,"remaining_time":1.022825473},
{"learn":[4.494692643],"iteration":285,"passed_time":0.4084889751,"remaining_time":1.019794155},
{"learn":[4.489330245],"iteration":286,"passed_time":0.4093844205,"remaining_time":1.017042132},
{"learn":[4.484826955],"iteration":287,"passed_time":0.4104076653,"remaining_time":1.01461895},
{"learn":[4.478285428],"iteration":288,"passed_time":0.4112665274,"remaining_time":1.011801041},
{"learn":[4.475311671],"iteration":289,"passed_time":0.4120721075,"remaining_time":1.008866194},
{"learn":[4.471581298],"iteration":290,"passed_time":0.4128104557,"remaining_time":1.005782176},
{"learn":[4.469164956],"iteration":291,"passed_time":0.414091705,"remaining_time":1.004030572},
{"learn":[4.462068024],"iteration":292,"passed_time":0.4149900058,"remaining_time":1.001358137},
{"learn":[4.458540976],"iteration":293,"passed_time":0.4160403451,"remaining_time":0.9990628694},
{"learn":[4.455757458],"iteration":294,"passed_time":0.4168901858,"remaining_time":0.9962968847},
{"learn":[4.453027414],"iteration":295,"passed_time":0.4178702715,"remaining_time":0.9938536187},
{"learn":[4.450659338],"iteration":296,"passed_time":0.4188599486,"remaining_time":0.9914429086},
{"learn":[4.444696901],"iteration":297,"passed_time":0.4200171229,"remaining_time":0.9894363096},
{"learn":[4.442052813],"iteration":298,"passed_time":0.4207958184,"remaining_time":0.9865480558},
{"learn":[4.440036756],"iteration":299,"passed_time":0.4217302461,"remaining_time":0.9840372409},
{"learn":[4.435017051],"iteration":300,"passed_time":0.4228303381,"remaining_time":0.9819216157},
{"learn":[4.429962125],"iteration":301,"passed_time":0.4239166924,"remaining_time":0.9797809646},
{"learn":[4.427666256],"iteration":302,"passed_time":0.4246243098,"remaining_time":0.9767760525},
{"learn":[4.425030004],"iteration":303,"passed_time":0.4255046869,"remaining_time":0.9741817831},
{"learn":[4.422588771],"iteration":304,"passed_time":0.4261866381,"remaining_time":0.9711466015},
{"learn":[4.418936667],"iteration":305,"passed_time":0.4270509289,"remaining_time":0.968540342},
{"learn":[4.416887976],"iteration":306,"passed_time":0.4278221118,"remaining_time":0.9657352557},
{"learn":[4.413773354],"iteration":307,"passed_time":0.428985158,"remaining_time":0.9638237965},
{"learn":[4.411129391],"iteration":308,"passed_time":0.4298668564,"remaining_time":0.9612880188},
{"learn":[4.40850819],"iteration":309,"passed_time":0.4310681095,"remaining_time":0.9594741792},
{"learn":[4.404880292],"iteration":310,"passed_time":0.4319243549,"remaining_time":0.9568999374},
{"learn":[4.404593827],"iteration":311,"passed_time":0.4324813767,"remaining_time":0.9536768819},
{"learn":[4.402139942],"iteration":312,"passed_time":0.4333059287,"remaining_time":0.9510580608},
{"learn":[4.400284725],"iteration":313,"passed_time":0.4342080609,"remaining_time":0.9486201585},
{"learn":[4.395805521],"iteration":314,"passed_time":0.4350615288,"remaining_time":0.9460861817},
{"learn":[4.392838833],"iteration":315,"passed_time":0.4359356681,"remaining_time":0.9436075855},
{"learn":[4.389213061],"iteration":316,"passed_time":0.4368891464,"remaining_time":0.9413100536},
{"learn":[4.3861981],"iteration":317,"passed_time":0.4379327802,"remaining_time":0.9392143274},
{"learn":[4.385054234],"iteration":318,"passed_time":0.4387349516,"remaining_time":0.9366097242},
{"learn":[4.379364607],"iteration":319,"passed_time":0.439552382,"remaining_time":0.9340488117},
{"learn":[4.378387619],"iteration":320,"passed_time":0.4406425282,"remaining_time":0.9320756282},
{"learn":[4.375816727],"iteration":321,"passed_time":0.4414782304,"remaining_time":0.9295721745},
{"learn":[4.374600202],"iteration":322,"passed_time":0.4422935327,"remaining_time":0.9270362899},
{"learn":[4.37098897],"iteration":323,"passed_time":0.4431580288,"remaining_time":0.9246136651},
{"learn":[4.367418484],"iteration":324,"passed_time":0.4442336862,"remaining_time":0.9226391944},
{"learn":[4.363584638],"iteration":325,"passed_time":0.4455635461,"remaining_time":0.9211957978},
{"learn":[4.360770706],"iteration":326,"passed_time":0.4468425034,"remaining_time":0.9196483326},
{"learn":[4.358675808],"iteration":327,"passed_time":0.4478446713,"remaining_time":0.9175354241},
{"learn":[4.354228195],"iteration":328,"passed_time":0.4486472138,"remaining_time":0.915022129},
{"learn":[4.353773425],"iteration":329,"passed_time":0.4496077146,"remaining_time":0.9128399053},
{"learn":[4.351648009],"iteration":330,"passed_time":0.4504326974,"remaining_time":0.9103911618},
{"learn":[4.348209927],"iteration":331,"passed_time":0.4514165343,"remaining_time":0.908271822},
{"learn":[4.345852733],"iteration":332,"passed_time":0.4522364274,"remaining_time":0.9058309222},
{"learn":[4.34237339],"iteration":333,"passed_time":0.4534130845,"remaining_time":0.9041111205},
{"learn":[4.340814362],"iteration":334,"passed_time":0.4542501467,"remaining_time":0.9017204405},
{"learn":[4.339707068],"iteration":335,"passed_time":0.4550060595,"remaining_time":0.8991786413},
{"learn":[4.335430786],"iteration":336,"passed_time":0.4556365207,"remaining_time":0.8964006327},
{"learn":[4.33521887],"iteration":337,"passed_time":0.4563568651,"remaining_time":0.8938113748},
{"learn":[4.328507238],"iteration":338,"passed_time":0.4571237979,"remaining_time":0.8913239835},
{"learn":[4.326140732],"iteration":339,"passed_time":0.4579644571,"remaining_time":0.8889898285},
{"learn":[4.323785636],"iteration":340,"passed_time":0.4589324689,"remaining_time":0.8869105485},
{"learn":[4.320632534],"iteration":341,"passed_time":0.4597847608,"remaining_time":0.8846151246},
{"learn":[4.31973724],"iteration":342,"passed_time":0.460747067,"remaining_time":0.8825388426},
{"learn":[4.318000924],"iteration":343,"passed_time":0.4618329079,"remaining_time":0.880704615},
{"learn":[4.312713628],"iteration":344,"passed_time":0.4627358077,"remaining_time":0.8785274029},
{"learn":[4.308220789],"iteration":345,"passed_time":0.4639232731,"remaining_time":0.8768954353},
{"learn":[4.305890947],"iteration":346,"passed_time":0.4650838353,"remaining_time":0.8752154019},
{"learn":[4.305137856],"iteration":347,"passed_time":0.4658095217,"remaining_time":0.8727235866},
{"learn":[4.304787172],"iteration":348,"passed_time":0.4667495765,"remaining_time":0.8706417601},
{"learn":[4.30350134],"iteration":349,"passed_time":0.4677981465,"remaining_time":0.8687679863},
{"learn":[4.30293809],"iteration":350,"passed_time":0.4689060692,"remaining_time":0.8670086579},
{"learn":[4.299548459],"iteration":351,"passed_time":0.4700155927,"remaining_time":0.8652559775},
{"learn":[4.294768408],"iteration":352,"passed_time":0.4709251335,"remaining_time":0.8631404005},
{"learn":[4.294581479],"iteration":353,"passed_time":0.4717356308,"remaining_time":0.8608508969},
{"learn":[4.292551604],"iteration":354,"passed_time":0.4728100235,"remaining_time":0.8590491976},
{"learn":[4.288628894],"iteration":355,"passed_time":0.4740058138,"remaining_time":0.8574711912},
{"learn":[4.287802767],"iteration":356,"passed_time":0.474923467,"remaining_time":0.8553943677},
{"learn":[4.284566905],"iteration":357,"passed_time":0.4759194873,"remaining_time":0.8534645555},
{"learn":[4.27890232],"iteration":358,"passed_time":0.4768212424,"remaining_time":0.8513716334},
{"learn":[4.276938023],"iteration":359,"passed_time":0.4775818189,"remaining_time":0.8490343448},
{"learn":[4.273425094],"iteration":360,"passed_time":0.4783683292,"remaining_time":0.8467516962},
{"learn":[4.269726505],"iteration":361,"passed_time":0.4792736816,"remaining_time":0.8446867648},
{"learn":[4.265565857],"iteration":362,"passed_time":0.4802585197,"remaining_time":0.8427677054},
{"learn":[4.262117173],"iteration":363,"passed_time":0.4811809001,"remaining_time":0.8407446496},
{"learn":[4.259185148],"iteration":364,"passed_time":0.4819959725,"remaining_time":0.8385409385},
{"learn":[4.257668507],"iteration":365,"passed_time":0.4825806521,"remaining_time":0.8359457198},
{"learn":[4.253432436],"iteration":366,"passed_time":0.4834675316,"remaining_time":0.8338826907},
{"learn":[4.250216667],"iteration":367,"passed_time":0.4840520986,"remaining_time":0.831306865},
{"learn":[4.24514828],"iteration":368,"passed_time":0.4848629231,"remaining_time":0.8291287384},
{"learn":[4.244015772],"iteration":369,"passed_time":0.4856714138,"remaining_time":0.826954029},
{"learn":[4.240329192],"iteration":370,"passed_time":0.4865071782,"remaining_time":0.8248329248},
{"learn":[4.236718014],"iteration":371,"passed_time":0.4873407918,"remaining_time":0.8227151002},
{"learn":[4.233495944],"iteration":372,"passed_time":0.4882994675,"remaining_time":0.8208143864},
{"learn":[4.230357491],"iteration":373,"passed_time":0.489074452,"remaining_time":0.8186112485},
{"learn":[4.227381215],"iteration":374,"passed_time":0.4899304359,"remaining_time":0.8165507264},
{"learn":[4.226169067],"iteration":375,"passed_time":0.4907604983,"remaining_time":0.8144535929},
{"learn":[4.225963861],"iteration":376,"passed_time":0.4915213998,"remaining_time":0.8122488914},
{"learn":[4.224346548],"iteration":377,"passed_time":0.4923331059,"remaining_time":0.8101354282},
{"learn":[4.222595381],"iteration":378,"passed_time":0.4932612813,"remaining_time":0.808219672},
{"learn":[4.219700938],"iteration":379,"passed_time":0.4939699539,"remaining_time":0.8059509775},
{"learn":[4.216356207],"iteration":380,"passed_time":0.4946803913,"remaining_time":0.8036933392},
{"learn":[4.214326494],"iteration":381,"passed_time":0.4954423473,"remaining_time":0.8015271482},
{"learn":[4.212901398],"iteration":382,"passed_time":0.4962281723,"remaining_time":0.7994067422},
{"learn":[4.211331091],"iteration":383,"passed_time":0.4969937248,"remaining_time":0.7972607669},
{"learn":[4.208624791],"iteration":384,"passed_time":0.4978441886,"remaining_time":0.7952576},
{"learn":[4.204659106],"iteration":385,"passed_time":0.4987151118,"remaining_time":0.7932929499},
{"learn":[4.202968852],"iteration":386,"passed_time":0.4993744173,"remaining_time":0.7909987541},
{"learn":[4.197261935],"iteration":387,"passed_time":0.5001390682,"remaining_time":0.7888791488},
{"learn":[4.196934403],"iteration":388,"passed_time":0.501020732,"remaining_time":0.7869503014},
{"learn":[4.192479929],"iteration":389,"passed_time":0.5021819623,"remaining_time":0.7854640949},
{"learn":[4.190243116],"iteration":390,"passed_time":0.5030522334,"remaining_time":0.7835263687},
{"learn":[4.185852431],"iteration":391,"passed_time":0.5037266199,"remaining_time":0.7812902676},
{"learn":[4.180967944],"iteration":392,"passed_time":0.5045287763,"remaining_time":0.7792594586},
{"learn":[4.178283162],"iteration":393,"passed_time":0.5053166194,"remaining_time":0.7772128715},
{"learn":[4.176341157],"iteration":394,"passed_time":0.5062840202,"remaining_time":0.7754476765},
{"learn":[4.176041504],"iteration":395,"passed_time":0.5070923775,"remaining_time":0.7734439293},
{"learn":[4.175564513],"iteration":396,"passed_time":0.5078981484,"remaining_time":0.7714422758},
{"learn":[4.170830274],"iteration":397,"passed_time":0.5085233899,"remaining_time":0.7691735697},
{"learn":[4.167804808],"iteration":398,"passed_time":0.5092522172,"remaining_time":0.7670691291},
{"learn":[4.165860548],"iteration":399,"passed_time":0.5099520667,"remaining_time":0.7649281001},
{"learn":[4.160950571],"iteration":400,"passed_time":0.5108127807,"remaining_time":0.7630345527},
{"learn":[4.158544115],"iteration":401,"passed_time":0.5117460328,"remaining_time":0.7612540488},
{"learn":[4.154448767],"iteration":402,"passed_time":0.5126927028,"remaining_time":0.7594976267},
{"learn":[4.15197457],"iteration":403,"passed_time":0.5134921327,"remaining_time":0.7575279978},
{"learn":[4.149562679],"iteration":404,"passed_time":0.5142720449,"remaining_time":0.7555354733},
{"learn":[4.149327961],"iteration":405,"passed_time":0.5148867783,"remaining_time":0.7533072569},
{"learn":[4.147444889],"iteration":406,"passed_time":0.5156013503,"remaining_time":0.7512324343},
{"learn":[4.147254809],"iteration":407,"passed_time":0.516248117,"remaining_time":0.7490658952},
{"learn":[4.144589165],"iteration":408,"passed_time":0.5169540061,"remaining_time":0.746992219},
{"learn":[4.141691034],"iteration":409,"passed_time":0.5177816222,"remaining_time":0.7451003832},
{"learn":[4.138893468],"iteration":410,"passed_time":0.5185774041,"remaining_time":0.7431681047},
{"learn":[4.136964597],"iteration":411,"passed_time":0.5192963702,"remaining_time":0.7411317128},
{"learn":[4.133773523],"iteration":412,"passed_time":0.520034266,"remaining_time":0.7391286057},
{"learn":[4.131363444],"iteration":413,"passed_time":0.520931108,"remaining_time":0.7373565925},
{"learn":[4.130228592],"iteration":414,"passed_time":0.5218415043,"remaining_time":0.7356079037},
{"learn":[4.12884186],"iteration":415,"passed_time":0.5226401041,"remaining_time":0.7337062999},
{"learn":[4.12413494],"iteration":416,"passed_time":0.523497492,"remaining_time":0.731892177},
{"learn":[4.119422508],"iteration":417,"passed_time":0.5243450537,"remaining_time":0.7300689504},
{"learn":[4.117038244],"iteration":418,"passed_time":0.5250799257,"remaining_time":0.7280941214},
{"learn":[4.116067631],"iteration":419,"passed_time":0.5257969631,"remaining_time":0.726100568},
{"learn":[4.110343455],"iteration":420,"passed_time":0.5264986873,"remaining_time":0.7240920189},
{"learn":[4.105604544],"iteration":421,"passed_time":0.5272473927,"remaining_time":0.7221540118},
{"learn":[4.103390131],"iteration":422,"passed_time":0.5280189975,"remaining_time":0.7202528642},
{"learn":[4.096724402],"iteration":423,"passed_time":0.5289047169,"remaining_time":0.7185120683},
{"learn":[4.093431279],"iteration":424,"passed_time":0.5299649196,"remaining_time":0.7170113618},
{"learn":[4.091412744],"iteration":425,"passed_time":0.5307842929,"remaining_time":0.7151882256},
{"learn":[4.091192901],"iteration":426,"passed_time":0.5316015619,"remaining_time":0.7133669672},
{"learn":[4.088994581],"iteration":427,"passed_time":0.5323669673,"remaining_time":0.7114810872},
{"learn":[4.087845355],"iteration":428,"passed_time":0.5330763051,"remaining_time":0.7095258047},
{"learn":[4.083650279],"iteration":429,"passed_time":0.5337683079,"remaining_time":0.7075533383},
{"learn":[4.079840652],"iteration":430,"passed_time":0.5343855494,"remaining_time":0.7054881152},
{"learn":[4.075707828],"iteration":431,"passed_time":0.5350588084,"remaining_time":0.703503248},
{"learn":[4.071345409],"iteration":432,"passed_time":0.535812849,"remaining_time":0.7016302203},
{"learn":[4.067460475],"iteration":433,"passed_time":0.5364727567,"remaining_time":0.6996395859},
{"learn":[4.064914749],"iteration":434,"passed_time":0.5372691889,"remaining_time":0.6978323947},
{"learn":[4.063823175],"iteration":435,"passed_time":0.5381330009,"remaining_time":0.6961170011},
{"learn":[4.058898471],"iteration":436,"passed_time":0.5388231077,"remaining_time":0.6941817154},
{"learn":[4.054120355],"iteration":437,"passed_time":0.5396565723,"remaining_time":0.6924360585},
{"learn":[4.052715901],"iteration":438,"passed_time":0.5405049441,"remaining_time":0.6907136074},
{"learn":[4.052114167],"iteration":439,"passed_time":0.5411682054,"remaining_time":0.6887595342},
{"learn":[4.051377267],"iteration":440,"passed_time":0.5419248377,"remaining_time":0.6869296696},
{"learn":[4.049275336],"iteration":441,"passed_time":0.5429747879,"remaining_time":0.6854749585},
{"learn":[4.047099198],"iteration":442,"passed_time":0.5437329528,"remaining_time":0.6836552025},
{"learn":[4.044348685],"iteration":443,"passed_time":0.5445692512,"remaining_time":0.6819380713},
{"learn":[4.042822379],"iteration":444,"passed_time":0.545426907,"remaining_time":0.6802515357},
{"learn":[4.041258611],"iteration":445,"passed_time":0.5460997717,"remaining_time":0.6783391783},
{"learn":[4.040044254],"iteration":446,"passed_time":0.5468920297,"remaining_time":0.6765800725},
{"learn":[4.036860137],"iteration":447,"passed_time":0.5477503834,"remaining_time":0.6749067224},
{"learn":[4.036372284],"iteration":448,"passed_time":0.548453884,"remaining_time":0.6730469712},
{"learn":[4.03368231],"iteration":449,"passed_time":0.5491387428,"remaining_time":0.6711695745},
{"learn":[4.032439519],"iteration":450,"passed_time":0.5498625932,"remaining_time":0.6693449305},
{"learn":[4.032008634],"iteration":451,"passed_time":0.5505618264,"remaining_time":0.6674953117},
{"learn":[4.030034932],"iteration":452,"passed_time":0.5514870689,"remaining_time":0.6659236792},
{"learn":[4.028173412],"iteration":453,"passed_time":0.5521898838,"remaining_time":0.6640873933},
{"learn":[4.023806097],"iteration":454,"passed_time":0.5530109056,"remaining_time":0.6623976782},
{"learn":[4.020239186],"iteration":455,"passed_time":0.5537672156,"remaining_time":0.660634573},
{"learn":[4.017384838],"iteration":456,"passed_time":0.5545382122,"remaining_time":0.6588933244},
{"learn":[4.016468229],"iteration":457,"passed_time":0.5553307396,"remaining_time":0.6571817923},
{"learn":[4.014530169],"iteration":458,"passed_time":0.5561506696,"remaining_time":0.6555065627},
{"learn":[4.012884822],"iteration":459,"passed_time":0.5569072099,"remaining_time":0.6537606377},
{"learn":[4.008924707],"iteration":460,"passed_time":0.5576175526,"remaining_time":0.651964991},
{"learn":[4.008286778],"iteration":461,"passed_time":0.5584150642,"remaining_time":0.650275551},
{"learn":[4.006444202],"iteration":462,"passed_time":0.55927277,"remaining_time":0.6486597786},
{"learn":[4.003284363],"iteration":463,"passed_time":0.5600625586,"remaining_time":0.6469688177},
{"learn":[3.999811484],"iteration":464,"passed_time":0.5610848815,"remaining_time":0.6455492723},
{"learn":[3.997483319],"iteration":465,"passed_time":0.5619059104,"remaining_time":0.6439007643},
{"learn":[3.99708333],"iteration":466,"passed_time":0.5626592445,"remaining_time":0.6421785382},
{"learn":[3.995860263],"iteration":467,"passed_time":0.5634114779,"remaining_time":0.6404592014},
{"learn":[3.994131111],"iteration":468,"passed_time":0.5641323235,"remaining_time":0.6387084516},
{"learn":[3.993125499],"iteration":469,"passed_time":0.5648565682,"remaining_time":0.6369659173},
{"learn":[3.992954084],"iteration":470,"passed_time":0.5656458124,"remaining_time":0.6353007107},
{"learn":[3.990635743],"iteration":471,"passed_time":0.5665035222,"remaining_time":0.6337158045},
{"learn":[3.986678254],"iteration":472,"passed_time":0.5674010078,"remaining_time":0.6321782898},
{"learn":[3.986393291],"iteration":473,"passed_time":0.5681622066,"remaining_time":0.6304922377},
{"learn":[3.986152671],"iteration":474,"passed_time":0.5688965614,"remaining_time":0.6287804099},
{"learn":[3.985596662],"iteration":475,"passed_time":0.5696794646,"remaining_time":0.6271261333},
{"learn":[3.983853457],"iteration":476,"passed_time":0.5703855131,"remaining_time":0.625391244},
{"learn":[3.983263928],"iteration":477,"passed_time":0.5711374522,"remaining_time":0.6237107741},
{"learn":[3.980067202],"iteration":478,"passed_time":0.5718202146,"remaining_time":0.621958939},
{"learn":[3.978115407],"iteration":479,"passed_time":0.5726519054,"remaining_time":0.6203728975},
{"learn":[3.972661644],"iteration":480,"passed_time":0.5733831655,"remaining_time":0.6186816277},
{"learn":[3.969938254],"iteration":481,"passed_time":0.5742004081,"remaining_time":0.6170867457},
{"learn":[3.968211434],"iteration":482,"passed_time":0.5752116428,"remaining_time":0.6157027315},
{"learn":[3.966113368],"iteration":483,"passed_time":0.5759974845,"remaining_time":0.6140799628},
{"learn":[3.962246044],"iteration":484,"passed_time":0.5767905437,"remaining_time":0.6124683092},
{"learn":[3.961319703],"iteration":485,"passed_time":0.5777299952,"remaining_time":0.6110148508},
{"learn":[3.96078191],"iteration":486,"passed_time":0.5786187322,"remaining_time":0.6095100813},
{"learn":[3.958913633],"iteration":487,"passed_time":0.579489557,"remaining_time":0.6079890434},
{"learn":[3.957428286],"iteration":488,"passed_time":0.5804158481,"remaining_time":0.6065286265},
{"learn":[3.952641965],"iteration":489,"passed_time":0.5812932743,"remaining_time":0.6050195304},
{"learn":[3.951486786],"iteration":490,"passed_time":0.5820918849,"remaining_time":0.6034313022},
{"learn":[3.94938344],"iteration":491,"passed_time":0.5828841488,"remaining_time":0.6018397309},
{"learn":[3.947297924],"iteration":492,"passed_time":0.5835744658,"remaining_time":0.6001465602},
{"learn":[3.946284886],"iteration":493,"passed_time":0.5843550539,"remaining_time":0.5985499135},
{"learn":[3.943288204],"iteration":494,"passed_time":0.585087038,"remaining_time":0.5969069782},
{"learn":[3.943076488],"iteration":495,"passed_time":0.5857323649,"remaining_time":0.5951796611},
{"learn":[3.942347078],"iteration":496,"passed_time":0.5864677772,"remaining_time":0.593547871},
{"learn":[3.940251541],"iteration":497,"passed_time":0.5871581858,"remaining_time":0.5918743158},
{"learn":[3.939011019],"iteration":498,"passed_time":0.5879022654,"remaining_time":0.5902585871},
{"learn":[3.938760512],"iteration":499,"passed_time":0.5887370297,"remaining_time":0.5887370297},
{"learn":[3.934522727],"iteration":500,"passed_time":0.5895323354,"remaining_time":0.5871789129},
{"learn":[3.930091193],"iteration":501,"passed_time":0.5904631617,"remaining_time":0.585758276},
{"learn":[3.927671752],"iteration":502,"passed_time":0.5911924413,"remaining_time":0.584140444},
{"learn":[3.927280041],"iteration":503,"passed_time":0.5919055854,"remaining_time":0.5825102587},
{"learn":[3.925987561],"iteration":504,"passed_time":0.5928307527,"remaining_time":0.5810915298},
{"learn":[3.921645957],"iteration":505,"passed_time":0.5935991566,"remaining_time":0.5795217062},
{"learn":[3.920333743],"iteration":506,"passed_time":0.5943847468,"remaining_time":0.5779717558},
{"learn":[3.918659461],"iteration":507,"passed_time":0.5951439409,"remaining_time":0.5763992498},
{"learn":[3.916124385],"iteration":508,"passed_time":0.5958171983,"remaining_time":0.574747042},
{"learn":[3.913849268],"iteration":509,"passed_time":0.5964872988,"remaining_time":0.57309564},
{"learn":[3.912826119],"iteration":510,"passed_time":0.5973708865,"remaining_time":0.5716523747},
{"learn":[3.910034145],"iteration":511,"passed_time":0.5981273693,"remaining_time":0.5700901489},
{"learn":[3.90792379],"iteration":512,"passed_time":0.5990500526,"remaining_time":0.5686888414},
{"learn":[3.907823851],"iteration":513,"passed_time":0.599701884,"remaining_time":0.5670332989},
{"learn":[3.904527401],"iteration":514,"passed_time":0.6003797151,"remaining_time":0.5654061394},
{"learn":[3.903378283],"iteration":515,"passed_time":0.6011112491,"remaining_time":0.5638330321},
{"learn":[3.902170135],"iteration":516,"passed_time":0.6017124941,"remaining_time":0.5621414597},
{"learn":[3.899435429],"iteration":517,"passed_time":0.6026847696,"remaining_time":0.5607993416},
{"learn":[3.897497505],"iteration":518,"passed_time":0.6035929726,"remaining_time":0.5593992675},
{"learn":[3.896426119],"iteration":519,"passed_time":0.6044736158,"remaining_time":0.5579756453},
{"learn":[3.896044669],"iteration":520,"passed_time":0.6051558937,"remaining_time":0.5563717334},
{"learn":[3.892795942],"iteration":521,"passed_time":0.6062143369,"remaining_time":0.5551158104},
{"learn":[3.892413888],"iteration":522,"passed_time":0.607247043,"remaining_time":0.5538371693},
{"learn":[3.891738985],"iteration":523,"passed_time":0.6080391486,"remaining_time":0.552340906},
{"learn":[3.88822057],"iteration":524,"passed_time":0.6087257662,"remaining_time":0.5507518837},
{"learn":[3.883837053],"iteration":525,"passed_time":0.6095019502,"remaining_time":0.5492470045},
{"learn":[3.881769742],"iteration":526,"passed_time":0.6102068481,"remaining_time":0.5476809092},
{"learn":[3.880356898],"iteration":527,"passed_time":0.6110780236,"remaining_time":0.546266718},
{"learn":[3.879250273],"iteration":528,"passed_time":0.6118343588,"remaining_time":0.5447523308},
{"learn":[3.877174493],"iteration":529,"passed_time":0.6125820865,"remaining_time":0.543233171},
{"learn":[3.875854201],"iteration":530,"passed_time":0.6133785305,"remaining_time":0.541759945},
{"learn":[3.873189396],"iteration":531,"passed_time":0.6141358127,"remaining_time":0.5402548126},
{"learn":[3.871583368],"iteration":532,"passed_time":0.6149167026,"remaining_time":0.5387731709},
{"learn":[3.869622679],"iteration":533,"passed_time":0.6156898042,"remaining_time":0.5372873572},
{"learn":[3.866860164],"iteration":534,"passed_time":0.6165328773,"remaining_time":0.5358650242},
{"learn":[3.864498444],"iteration":535,"passed_time":0.6170925052,"remaining_time":0.5341994821},
{"learn":[3.861416322],"iteration":536,"passed_time":0.617922056,"remaining_time":0.5327707857},
{"learn":[3.860265769],"iteration":537,"passed_time":0.6186730091,"remaining_time":0.5312768219},
{"learn":[3.859328725],"iteration":538,"passed_time":0.6193556995,"remaining_time":0.529727231},
{"learn":[3.858521278],"iteration":539,"passed_time":0.6201814556,"remaining_time":0.5283027214},
{"learn":[3.85599111],"iteration":540,"passed_time":0.6210351206,"remaining_time":0.5269041041},
{"learn":[3.852379816],"iteration":541,"passed_time":0.6218318564,"remaining_time":0.5254593916},
{"learn":[3.851327537],"iteration":542,"passed_time":0.6226160623,"remaining_time":0.5240065202},
{"learn":[3.847854898],"iteration":543,"passed_time":0.6233370398,"remaining_time":0.5225031069},
{"learn":[3.847083414],"iteration":544,"passed_time":0.6241213251,"remaining_time":0.5210554182},
{"learn":[3.845397429],"iteration":545,"passed_time":0.6248684505,"remaining_time":0.519579261},
{"learn":[3.841933528],"iteration":546,"passed_time":0.6257937388,"remaining_time":0.5182533157},
{"learn":[3.840996474],"iteration":547,"passed_time":0.6266108197,"remaining_time":0.5168395812},
{"learn":[3.838355966],"iteration":548,"passed_time":0.6274117234,"remaining_time":0.5154147309},
{"learn":[3.83342799],"iteration":549,"passed_time":0.6281946255,"remaining_time":0.5139774208},
{"learn":[3.828161535],"iteration":550,"passed_time":0.6290479201,"remaining_time":0.5125998478},
{"learn":[3.823502399],"iteration":551,"passed_time":0.6298122922,"remaining_time":0.5111520053},
{"learn":[3.820068862],"iteration":552,"passed_time":0.6306109199,"remaining_time":0.509734324},
{"learn":[3.817951642],"iteration":553,"passed_time":0.6315054102,"remaining_time":0.5083960523},
{"learn":[3.815785958],"iteration":554,"passed_time":0.6321832059,"remaining_time":0.5068856335},
{"learn":[3.81503012],"iteration":555,"passed_time":0.6328521751,"remaining_time":0.5053711614},
{"learn":[3.813529315],"iteration":556,"passed_time":0.6337640973,"remaining_time":0.5040529535},
{"learn":[3.808881326],"iteration":557,"passed_time":0.634724736,"remaining_time":0.5027747909},
{"learn":[3.808740434],"iteration":558,"passed_time":0.6355272129,"remaining_time":0.501372989},
{"learn":[3.80714352],"iteration":559,"passed_time":0.6363666033,"remaining_time":0.5000023312},
{"learn":[3.80573346],"iteration":560,"passed_time":0.6373289765,"remaining_time":0.4987298052},
{"learn":[3.803370052],"iteration":561,"passed_time":0.6382360993,"remaining_time":0.497415323},
{"learn":[3.803215211],"iteration":562,"passed_time":0.6391365651,"remaining_time":0.4960971207},
{"learn":[3.801309667],"iteration":563,"passed_time":0.6399805388,"remaining_time":0.4947367286},
{"learn":[3.800003847],"iteration":564,"passed_time":0.6406976861,"remaining_time":0.4932805194},
{"learn":[3.798026138],"iteration":565,"passed_time":0.6414754653,"remaining_time":0.4918734133},
{"learn":[3.794745847],"iteration":566,"passed_time":0.6422455513,"remaining_time":0.490462652},
{"learn":[3.794312041],"iteration":567,"passed_time":0.6431753584,"remaining_time":0.4891756247},
{"learn":[3.792205926],"iteration":568,"passed_time":0.6440928011,"remaining_time":0.4878804873},
{"learn":[3.788991061],"iteration":569,"passed_time":0.6450464146,"remaining_time":0.4866139619},
{"learn":[3.787391572],"iteration":570,"passed_time":0.6459098727,"remaining_time":0.4852807975},
{"learn":[3.7826445],"iteration":571,"passed_time":0.6467422588,"remaining_time":0.4839260258},
{"learn":[3.781700331],"iteration":572,"passed_time":0.6475380441,"remaining_time":0.4825458025},
{"learn":[3.780045374],"iteration":573,"passed_time":0.6483689643,"remaining_time":0.4811936913},
{"learn":[3.775462644],"iteration":574,"passed_time":0.6491248696,"remaining_time":0.4797879471},
{"learn":[3.773711943],"iteration":575,"passed_time":0.6499236765,"remaining_time":0.4784160397},
{"learn":[3.772415806],"iteration":576,"passed_time":0.65070081,"remaining_time":0.4770302298},
{"learn":[3.770170875],"iteration":577,"passed_time":0.6514463696,"remaining_time":0.475623474},
{"learn":[3.765166479],"iteration":578,"passed_time":0.6522588199,"remaining_time":0.4742676393},
{"learn":[3.763976102],"iteration":579,"passed_time":0.6534333615,"remaining_time":0.4731758825},
{"learn":[3.760761708],"iteration":580,"passed_time":0.6544990131,"remaining_time":0.4720053124},
{"learn":[3.758155662],"iteration":581,"passed_time":0.6553416793,"remaining_time":0.4706749518},
{"learn":[3.756844548],"iteration":582,"passed_time":0.6561131842,"remaining_time":0.469295365},
{"learn":[3.753098923],"iteration":583,"passed_time":0.6568751324,"remaining_time":0.4679110532},
{"learn":[3.751618946],"iteration":584,"passed_time":0.6577747788,"remaining_time":0.4666265525},
{"learn":[3.751398464],"iteration":585,"passed_time":0.6586368059,"remaining_time":0.4653167878},
{"learn":[3.749920103],"iteration":586,"passed_time":0.6594319152,"remaining_time":0.4639614668},
{"learn":[3.748237465],"iteration":587,"passed_time":0.660216433,"remaining_time":0.4626006299},
{"learn":[3.746021536],"iteration":588,"passed_time":0.6610407745,"remaining_time":0.4612695388},
{"learn":[3.74417648],"iteration":589,"passed_time":0.6618631967,"remaining_time":0.4599388316},
{"learn":[3.738788389],"iteration":590,"passed_time":0.6628065123,"remaining_time":0.4586935085},
{"learn":[3.736021611],"iteration":591,"passed_time":0.6636552881,"remaining_time":0.4573840499},
{"learn":[3.734546151],"iteration":592,"passed_time":0.6645690171,"remaining_time":0.4561207251},
{"learn":[3.733527479],"iteration":593,"passed_time":0.6652015144,"remaining_time":0.454666355},
{"learn":[3.733026392],"iteration":594,"passed_time":0.6659784705,"remaining_time":0.4533130766},
{"learn":[3.730314752],"iteration":595,"passed_time":0.6666924687,"remaining_time":0.4519190559},
{"learn":[3.727342596],"iteration":596,"passed_time":0.6677070823,"remaining_time":0.4507302415},
{"learn":[3.725459604],"iteration":597,"passed_time":0.6684631232,"remaining_time":0.4493681865},
{"learn":[3.723158842],"iteration":598,"passed_time":0.6691281784,"remaining_time":0.4479472446},
{"learn":[3.722362756],"iteration":599,"passed_time":0.6698788334,"remaining_time":0.4465858889},
{"learn":[3.721443615],"iteration":600,"passed_time":0.670511242,"remaining_time":0.4451480625},
{"learn":[3.720743486],"iteration":601,"passed_time":0.6713645951,"remaining_time":0.4438589848},
{"learn":[3.720215334],"iteration":602,"passed_time":0.6720306302,"remaining_time":0.4424480269},
{"learn":[3.719436563],"iteration":603,"passed_time":0.6728067546,"remaining_time":0.4411117133},
{"learn":[3.715046574],"iteration":604,"passed_time":0.6735806816,"remaining_time":0.4397758169},
{"learn":[3.71443396],"iteration":605,"passed_time":0.6748193635,"remaining_time":0.4387439426},
{"learn":[3.712938941],"iteration":606,"passed_time":0.6758064617,"remaining_time":0.4375484999},
{"learn":[3.712814764],"iteration":607,"passed_time":0.676623161,"remaining_time":0.4362438801},
{"learn":[3.71235348],"iteration":608,"passed_time":0.6774593189,"remaining_time":0.4349533558},
{"learn":[3.711223749],"iteration":609,"passed_time":0.678255172,"remaining_time":0.4336385526},
{"learn":[3.710755648],"iteration":610,"passed_time":0.6791182201,"remaining_time":0.4323682285},
{"learn":[3.708668039],"iteration":611,"passed_time":0.680049767,"remaining_time":0.4311426628},
{"learn":[3.705623591],"iteration":612,"passed_time":0.6810482486,"remaining_time":0.4299603135},
{"learn":[3.704045802],"iteration":613,"passed_time":0.6818029756,"remaining_time":0.4286253234},
{"learn":[3.699915209],"iteration":614,"passed_time":0.6824630376,"remaining_time":0.4272329585},
{"learn":[3.696182221],"iteration":615,"passed_time":0.6834014312,"remaining_time":0.4260164766},
{"learn":[3.694263278],"iteration":616,"passed_time":0.6842324043,"remaining_time":0.4247342153},
{"learn":[3.693810229],"iteration":617,"passed_time":0.6850082179,"remaining_time":0.4234193192},
{"learn":[3.690900932],"iteration":618,"passed_time":0.6857165991,"remaining_time":0.4220646596},
{"learn":[3.688020895],"iteration":619,"passed_time":0.6864894157,"remaining_time":0.4207515774},
{"learn":[3.685491894],"iteration":620,"passed_time":0.6873975703,"remaining_time":0.4195228327},
{"learn":[3.684328128],"iteration":621,"passed_time":0.6882187277,"remaining_time":0.4182422493},
{"learn":[3.680640153],"iteration":622,"passed_time":0.6890787855,"remaining_time":0.4169866808},
{"learn":[3.678932783],"iteration":623,"passed_time":0.689875265,"remaining_time":0.4156940699},
{"learn":[3.674167041],"iteration":624,"passed_time":0.6905946715,"remaining_time":0.4143568029},
{"learn":[3.672200976],"iteration":625,"passed_time":0.6915192753,"remaining_time":0.4131441038},
{"learn":[3.670606604],"iteration":626,"passed_time":0.6924337779,"remaining_time":0.4119263145},
{"learn":[3.665506042],"iteration":627,"passed_time":0.6932994173,"remaining_time":0.4106805465},
{"learn":[3.664214007],"iteration":628,"passed_time":0.6942025626,"remaining_time":0.4094581093},
{"learn":[3.66261643],"iteration":629,"passed_time":0.6949646312,"remaining_time":0.408153831},
{"learn":[3.662118449],"iteration":630,"passed_time":0.6957806381,"remaining_time":0.4068828137},
{"learn":[3.660871366],"iteration":631,"passed_time":0.6966109391,"remaining_time":0.4056215595},
{"learn":[3.656695243],"iteration":632,"passed_time":0.6974621414,"remaining_time":0.404373785},
{"learn":[3.654497801],"iteration":633,"passed_time":0.6981942187,"remaining_time":0.4030584922},
{"learn":[3.654189134],"iteration":634,"passed_time":0.699235246,"remaining_time":0.4019226217},
{"learn":[3.653957699],"iteration":635,"passed_time":0.7001018996,"remaining_time":0.4006872507},
{"learn":[3.651920725],"iteration":636,"passed_time":0.7011085126,"remaining_time":0.3995327945},
{"learn":[3.65106705],"iteration":637,"passed_time":0.7019092069,"remaining_time":0.3982619638},
{"learn":[3.650612844],"iteration":638,"passed_time":0.7027637255,"remaining_time":0.3970230124},
{"learn":[3.649884732],"iteration":639,"passed_time":0.7035435073,"remaining_time":0.3957432228},
{"learn":[3.646276182],"iteration":640,"passed_time":0.7046494957,"remaining_time":0.3946476895},
{"learn":[3.645808194],"iteration":641,"passed_time":0.7055161758,"remaining_time":0.3934186775},
{"learn":[3.645042989],"iteration":642,"passed_time":0.7062877388,"remaining_time":0.3921379825},
{"learn":[3.639864499],"iteration":643,"passed_time":0.7072263698,"remaining_time":0.3909512231},
{"learn":[3.637318478],"iteration":644,"passed_time":0.7081227017,"remaining_time":0.3897419521},
{"learn":[3.636344905],"iteration":645,"passed_time":0.7089609537,"remaining_time":0.3885018229},
{"learn":[3.634754643],"iteration":646,"passed_time":0.709619315,"remaining_time":0.3871647886},
{"learn":[3.630724975],"iteration":647,"passed_time":0.7104325459,"remaining_time":0.3859139756},
{"learn":[3.629408252],"iteration":648,"passed_time":0.7113339843,"remaining_time":0.3847122165},
{"learn":[3.62790646],"iteration":649,"passed_time":0.7124230484,"remaining_time":0.3836124107},
{"learn":[3.627388973],"iteration":650,"passed_time":0.7131638168,"remaining_time":0.3823259172},
{"learn":[3.625163557],"iteration":651,"passed_time":0.7139444034,"remaining_time":0.3810623503},
{"learn":[3.623701985],"iteration":652,"passed_time":0.7148479012,"remaining_time":0.3798655769},
{"learn":[3.622342639],"iteration":653,"passed_time":0.7156641046,"remaining_time":0.3786235171},
{"learn":[3.621130639],"iteration":654,"passed_time":0.7166223532,"remaining_time":0.3774575754},
{"learn":[3.619125665],"iteration":655,"passed_time":0.7175572673,"remaining_time":0.3762800304},
{"learn":[3.618878783],"iteration":656,"passed_time":0.7184899302,"remaining_time":0.3751020488},
{"learn":[3.616207429],"iteration":657,"passed_time":0.7192337438,"remaining_time":0.3738266571},
{"learn":[3.61206486],"iteration":658,"passed_time":0.7199406106,"remaining_time":0.3725337606},
{"learn":[3.611955873],"iteration":659,"passed_time":0.720636564,"remaining_time":0.3712370178},
{"learn":[3.610713743],"iteration":660,"passed_time":0.7215037755,"remaining_time":0.3700299242},
{"learn":[3.610044025],"iteration":661,"passed_time":0.7222753516,"remaining_time":0.3687750284},
{"learn":[3.607342669],"iteration":662,"passed_time":0.7230725305,"remaining_time":0.3675346045},
{"learn":[3.602510618],"iteration":663,"passed_time":0.7238396786,"remaining_time":0.3662803193},
{"learn":[3.600492392],"iteration":664,"passed_time":0.7246104569,"remaining_time":0.3650293279},
{"learn":[3.597171065],"iteration":665,"passed_time":0.7253323459,"remaining_time":0.3637552605},
{"learn":[3.594358798],"iteration":666,"passed_time":0.726021618,"remaining_time":0.3624665649},
{"learn":[3.593945251],"iteration":667,"passed_time":0.7268459719,"remaining_time":0.3612468004},
{"learn":[3.593607748],"iteration":668,"passed_time":0.727649121,"remaining_time":0.3600177265},
{"learn":[3.592238714],"iteration":669,"passed_time":0.7282365245,"remaining_time":0.3586836613},
{"learn":[3.590144654],"iteration":670,"passed_time":0.729172066,"remaining_time":0.3575225182},
{"learn":[3.587151536],"iteration":671,"passed_time":0.7299126239,"remaining_time":0.3562668759},
{"learn":[3.586070865],"iteration":672,"passed_time":0.7306633593,"remaining_time":0.3550177095},
{"learn":[3.585102746],"iteration":673,"passed_time":0.7313978725,"remaining_time":0.3537621757},
{"learn":[3.584362847],"iteration":674,"passed_time":0.7321774746,"remaining_time":0.3525298952},
{"learn":[3.581407561],"iteration":675,"passed_time":0.7330311746,"remaining_time":0.3513344683},
{"learn":[3.57919422],"iteration":676,"passed_time":0.7339112876,"remaining_time":0.3501526527},
{"learn":[3.577632204],"iteration":677,"passed_time":0.73459211,"remaining_time":0.3488770788},
{"learn":[3.573911195],"iteration":678,"passed_time":0.7354944852,"remaining_time":0.3477079967},
{"learn":[3.573408216],"iteration":679,"passed_time":0.7363719502,"remaining_time":0.3465279766},
{"learn":[3.571076482],"iteration":680,"passed_time":0.7372278327,"remaining_time":0.3453387352},
{"learn":[3.568177107],"iteration":681,"passed_time":0.7382869823,"remaining_time":0.3442452498},
{"learn":[3.564824621],"iteration":682,"passed_time":0.7391831946,"remaining_time":0.3430762411},
{"learn":[3.562475026],"iteration":683,"passed_time":0.7402276158,"remaining_time":0.3419765009},
{"learn":[3.561226889],"iteration":684,"passed_time":0.741044915,"remaining_time":0.3407724792},
{"learn":[3.559383467],"iteration":685,"passed_time":0.7418227703,"remaining_time":0.3395515304},
{"learn":[3.555209766],"iteration":686,"passed_time":0.7426500574,"remaining_time":0.338354393},
{"learn":[3.55345383],"iteration":687,"passed_time":0.743432092,"remaining_time":0.3371378092},
{"learn":[3.552300968],"iteration":688,"passed_time":0.7441722784,"remaining_time":0.3359035974},
{"learn":[3.551253986],"iteration":689,"passed_time":0.7451606319,"remaining_time":0.3347823129},
{"learn":[3.549807725],"iteration":690,"passed_time":0.7459050778,"remaining_time":0.333552343},
{"learn":[3.547992926],"iteration":691,"passed_time":0.7467789325,"remaining_time":0.3323813746},
{"learn":[3.545438607],"iteration":692,"passed_time":0.7477083696,"remaining_time":0.3312358867},
{"learn":[3.543313763],"iteration":693,"passed_time":0.7485622194,"remaining_time":0.3300576933},
{"learn":[3.542962896],"iteration":694,"passed_time":0.7497730251,"remaining_time":0.329037083},
{"learn":[3.539800465],"iteration":695,"passed_time":0.7505922136,"remaining_time":0.3278448749},
{"learn":[3.53953187],"iteration":696,"passed_time":0.7512201328,"remaining_time":0.3265705886},
{"learn":[3.536332425],"iteration":697,"passed_time":0.7520315825,"remaining_time":0.3253775615},
{"learn":[3.534993327],"iteration":698,"passed_time":0.7528113218,"remaining_time":0.3241719712},
{"learn":[3.531637011],"iteration":699,"passed_time":0.7536824253,"remaining_time":0.3230067537},
{"learn":[3.531040284],"iteration":700,"passed_time":0.7542878282,"remaining_time":0.3217290451},
{"learn":[3.529973872],"iteration":701,"passed_time":0.75504109,"remaining_time":0.3205160183},
{"learn":[3.527325183],"iteration":702,"passed_time":0.7558368202,"remaining_time":0.3193222412},
{"learn":[3.527200815],"iteration":703,"passed_time":0.7565299885,"remaining_time":0.3180864724},
{"learn":[3.523459911],"iteration":704,"passed_time":0.7572231137,"remaining_time":0.3168522249},
{"learn":[3.522729934],"iteration":705,"passed_time":0.7579031104,"remaining_time":0.3156140431},
{"learn":[3.522260582],"iteration":706,"passed_time":0.7587583393,"remaining_time":0.3144500614},
{"learn":[3.518641591],"iteration":707,"passed_time":0.7594988622,"remaining_time":0.3132396437},
{"learn":[3.516856405],"iteration":708,"passed_time":0.7602418701,"remaining_time":0.3120315715},
{"learn":[3.515083413],"iteration":709,"passed_time":0.7609575727,"remaining_time":0.3108136565},
{"learn":[3.514671214],"iteration":710,"passed_time":0.7617177192,"remaining_time":0.3096152192},
{"learn":[3.512617621],"iteration":711,"passed_time":0.7623934296,"remaining_time":0.3083838592},
{"learn":[3.510747971],"iteration":712,"passed_time":0.763175813,"remaining_time":0.3071969963},
{"learn":[3.508149266],"iteration":713,"passed_time":0.7640424465,"remaining_time":0.3060450136},
{"learn":[3.504557165],"iteration":714,"passed_time":0.7647916267,"remaining_time":0.304847012},
{"learn":[3.501367208],"iteration":715,"passed_time":0.7653701374,"remaining_time":0.3035825685},
{"learn":[3.497593362],"iteration":716,"passed_time":0.7661541946,"remaining_time":0.3024011675},
{"learn":[3.496291169],"iteration":717,"passed_time":0.7670251279,"remaining_time":0.3012549945},
{"learn":[3.49330374],"iteration":718,"passed_time":0.7678946854,"remaining_time":0.3001090495},
{"learn":[3.490044385],"iteration":719,"passed_time":0.7687413067,"remaining_time":0.2989549526},
{"learn":[3.488891789],"iteration":720,"passed_time":0.7696652345,"remaining_time":0.2978316234},
{"learn":[3.486869081],"iteration":721,"passed_time":0.7704602924,"remaining_time":0.2966592262},
{"learn":[3.486303638],"iteration":722,"passed_time":0.7711268307,"remaining_time":0.2954386336},
{"learn":[3.486035862],"iteration":723,"passed_time":0.7719974938,"remaining_time":0.2942973871},
{"learn":[3.482668951],"iteration":724,"passed_time":0.7728541364,"remaining_time":0.293151569},
{"learn":[3.47820549],"iteration":725,"passed_time":0.7736885653,"remaining_time":0.2919981638},
{"learn":[3.474392283],"iteration":726,"passed_time":0.7746027054,"remaining_time":0.2908755689},
{"learn":[3.472268163],"iteration":727,"passed_time":0.7756162765,"remaining_time":0.2897906967},
{"learn":[3.471209164],"iteration":728,"passed_time":0.7764757906,"remaining_time":0.2886487507},
{"learn":[3.470049971],"iteration":729,"passed_time":0.777276075,"remaining_time":0.2874856716},
{"learn":[3.469078654],"iteration":730,"passed_time":0.7782990149,"remaining_time":0.2864055199},
{"learn":[3.468643292],"iteration":731,"passed_time":0.7792133,"remaining_time":0.2852857437},
{"learn":[3.468134848],"iteration":732,"passed_time":0.7798893372,"remaining_time":0.2840797449},
{"learn":[3.467820182],"iteration":733,"passed_time":0.7806238045,"remaining_time":0.2828963651},
{"learn":[3.465776156],"iteration":734,"passed_time":0.7814387465,"remaining_time":0.2817432215},
{"learn":[3.463037608],"iteration":735,"passed_time":0.7823728348,"remaining_time":0.2806337342},
{"learn":[3.45965637],"iteration":736,"passed_time":0.7831080153,"remaining_time":0.2794537422},
{"learn":[3.457275091],"iteration":737,"passed_time":0.7840458183,"remaining_time":0.2783468894},
{"learn":[3.455522955],"iteration":738,"passed_time":0.784738307,"remaining_time":0.277153854},
{"learn":[3.451270508],"iteration":739,"passed_time":0.7855770647,"remaining_time":0.2760135633},
{"learn":[3.450978947],"iteration":740,"passed_time":0.7863238939,"remaining_time":0.2748419548},
{"learn":[3.450608492],"iteration":741,"passed_time":0.7871557271,"remaining_time":0.273701048},
{"learn":[3.448122004],"iteration":742,"passed_time":0.787950817,"remaining_time":0.2725482638},
{"learn":[3.445646714],"iteration":743,"passed_time":0.7889335216,"remaining_time":0.2714609967},
{"learn":[3.44411263],"iteration":744,"passed_time":0.7897347394,"remaining_time":0.2703118907},
{"learn":[3.443264164],"iteration":745,"passed_time":0.7904785894,"remaining_time":0.2691441846},
{"learn":[3.439521363],"iteration":746,"passed_time":0.7911588559,"remaining_time":0.2679560784},
{"learn":[3.436809225],"iteration":747,"passed_time":0.791848576,"remaining_time":0.2667725149},
{"learn":[3.435509465],"iteration":748,"passed_time":0.7925014578,"remaining_time":0.2655779251},
{"learn":[3.434450277],"iteration":749,"passed_time":0.7931934248,"remaining_time":0.2643978083},
{"learn":[3.431786753],"iteration":750,"passed_time":0.7938187319,"remaining_time":0.2631968898},
{"learn":[3.430150302],"iteration":751,"passed_time":0.7944431298,"remaining_time":0.2619972024},
{"learn":[3.42696281],"iteration":752,"passed_time":0.7952192195,"remaining_time":0.2608488011},
{"learn":[3.426870334],"iteration":753,"passed_time":0.7957379308,"remaining_time":0.2596174151},
{"learn":[3.425200309],"iteration":754,"passed_time":0.7964980799,"remaining_time":0.2584662643},
{"learn":[3.423383783],"iteration":755,"passed_time":0.7971141365,"remaining_time":0.2572696419},
{"learn":[3.422752979],"iteration":756,"passed_time":0.7977167651,"remaining_time":0.256070243},
{"learn":[3.420845924],"iteration":757,"passed_time":0.7983871477,"remaining_time":0.2548940498},
{"learn":[3.418917862],"iteration":758,"passed_time":0.7991177036,"remaining_time":0.2537382959},
{"learn":[3.417095735],"iteration":759,"passed_time":0.7999946537,"remaining_time":0.2526298906},
{"learn":[3.414391848],"iteration":760,"passed_time":0.8009774674,"remaining_time":0.2515553413},
{"learn":[3.41426711],"iteration":761,"passed_time":0.801761649,"remaining_time":0.2504189927},
{"learn":[3.411976013],"iteration":762,"passed_time":0.8025214803,"remaining_time":0.2492760037},
{"learn":[3.408614844],"iteration":763,"passed_time":0.8036539051,"remaining_time":0.248249112},
{"learn":[3.407906721],"iteration":764,"passed_time":0.8043685755,"remaining_time":0.2470936147},
{"learn":[3.407494015],"iteration":765,"passed_time":0.8051022715,"remaining_time":0.2459450803},
{"learn":[3.406287128],"iteration":766,"passed_time":0.8059567823,"remaining_time":0.2448343289},
{"learn":[3.404600442],"iteration":767,"passed_time":0.8067185144,"remaining_time":0.2436962179},
{"learn":[3.404012662],"iteration":768,"passed_time":0.8076261614,"remaining_time":0.2426029172},
{"learn":[3.400398762],"iteration":769,"passed_time":0.8085112333,"remaining_time":0.2415033554},
{"learn":[3.399737714],"iteration":770,"passed_time":0.8092202279,"remaining_time":0.2403520521},
{"learn":[3.399185251],"iteration":771,"passed_time":0.8102447359,"remaining_time":0.2392950774},
{"learn":[3.397245411],"iteration":772,"passed_time":0.810981661,"remaining_time":0.2381537349},
{"learn":[3.396229831],"iteration":773,"passed_time":0.8117868667,"remaining_time":0.2370333745},
{"learn":[3.394002836],"iteration":774,"passed_time":0.8126550947,"remaining_time":0.2359321243},
{"learn":[3.389617243],"iteration":775,"passed_time":0.8133711542,"remaining_time":0.2347875497},
{"learn":[3.385426488],"iteration":776,"passed_time":0.8141952241,"remaining_time":0.2336750772},
{"learn":[3.385072258],"iteration":777,"passed_time":0.8149794285,"remaining_time":0.2325519706},
{"learn":[3.383842366],"iteration":778,"passed_time":0.815906751,"remaining_time":0.2314703363},
{"learn":[3.380110746],"iteration":779,"passed_time":0.8168999133,"remaining_time":0.2304076678},
{"learn":[3.378595218],"iteration":780,"passed_time":0.8176022617,"remaining_time":0.2292636304},
{"learn":[3.377371219],"iteration":781,"passed_time":0.8185777447,"remaining_time":0.2281968649},
{"learn":[3.375814782],"iteration":782,"passed_time":0.8192566921,"remaining_time":0.2270481509},
{"learn":[3.374195887],"iteration":783,"passed_time":0.8201525746,"remaining_time":0.2259604032},
{"learn":[3.373704309],"iteration":784,"passed_time":0.8209652801,"remaining_time":0.2248503633},
{"learn":[3.372971757],"iteration":785,"passed_time":0.8217813564,"remaining_time":0.2237419978},
{"learn":[3.371565136],"iteration":786,"passed_time":0.8227373413,"remaining_time":0.222672241},
{"learn":[3.3700309],"iteration":787,"passed_time":0.8234417641,"remaining_time":0.2215350939},
{"learn":[3.368186663],"iteration":788,"passed_time":0.8240782101,"remaining_time":0.2203808648},
{"learn":[3.366710398],"iteration":789,"passed_time":0.8247050763,"remaining_time":0.2192254},
{"learn":[3.364598042],"iteration":790,"passed_time":0.8254050887,"remaining_time":0.2180905986},
{"learn":[3.36348442],"iteration":791,"passed_time":0.8262066347,"remaining_time":0.2169835606},
{"learn":[3.362001759],"iteration":792,"passed_time":0.8270213319,"remaining_time":0.215880726},
{"learn":[3.361580401],"iteration":793,"passed_time":0.8279735515,"remaining_time":0.2148142967},
{"learn":[3.359543675],"iteration":794,"passed_time":0.8289011676,"remaining_time":0.2137418105},
{"learn":[3.35766119],"iteration":795,"passed_time":0.8297324188,"remaining_time":0.2126449917},
{"learn":[3.354592969],"iteration":796,"passed_time":0.8305295492,"remaining_time":0.2115401487},
{"learn":[3.350985986],"iteration":797,"passed_time":0.8313301652,"remaining_time":0.2104369591},
{"learn":[3.349589624],"iteration":798,"passed_time":0.8322520291,"remaining_time":0.2093650286},
{"learn":[3.349110856],"iteration":799,"passed_time":0.8329289282,"remaining_time":0.2082322321},
{"learn":[3.345315441],"iteration":800,"passed_time":0.8335729203,"remaining_time":0.2070923984},
{"learn":[3.34397474],"iteration":801,"passed_time":0.8344137084,"remaining_time":0.2060023869},
{"learn":[3.343800902],"iteration":802,"passed_time":0.8351704253,"remaining_time":0.2048923708},
{"learn":[3.342329465],"iteration":803,"passed_time":0.8359425167,"remaining_time":0.2037869817},
{"learn":[3.34220347],"iteration":804,"passed_time":0.8367055876,"remaining_time":0.2026802355},
{"learn":[3.341279219],"iteration":805,"passed_time":0.8375205076,"remaining_time":0.2015868219},
{"learn":[3.337329521],"iteration":806,"passed_time":0.8382690941,"remaining_time":0.2004782344},
{"learn":[3.336708453],"iteration":807,"passed_time":0.8389459746,"remaining_time":0.1993534989},
{"learn":[3.333252703],"iteration":808,"passed_time":0.8396540253,"remaining_time":0.1982372297},
{"learn":[3.332186769],"iteration":809,"passed_time":0.8404493739,"remaining_time":0.1971424457},
{"learn":[3.330594851],"iteration":810,"passed_time":0.841206884,"remaining_time":0.1960395821},
{"learn":[3.327867442],"iteration":811,"passed_time":0.8419954866,"remaining_time":0.1949447678},
{"learn":[3.327563111],"iteration":812,"passed_time":0.8428722816,"remaining_time":0.1938709922},
{"learn":[3.326308994],"iteration":813,"passed_time":0.8435905285,"remaining_time":0.1927614721},
{"learn":[3.326249879],"iteration":814,"passed_time":0.8442675472,"remaining_time":0.1916435537},
{"learn":[3.322336238],"iteration":815,"passed_time":0.8450667055,"remaining_time":0.1905542571},
{"learn":[3.320491154],"iteration":816,"passed_time":0.8460229282,"remaining_time":0.1895008517},
{"learn":[3.320434271],"iteration":817,"passed_time":0.8468037111,"remaining_time":0.1884086497},
{"learn":[3.319609638],"iteration":818,"passed_time":0.8476900883,"remaining_time":0.1873405445},
{"learn":[3.316182682],"iteration":819,"passed_time":0.8484426027,"remaining_time":0.1862434981},
{"learn":[3.313126612],"iteration":820,"passed_time":0.8491366668,"remaining_time":0.1851345473},
{"learn":[3.311222803],"iteration":821,"passed_time":0.8499245979,"remaining_time":0.1840469324},
{"learn":[3.309627335],"iteration":822,"passed_time":0.8509430328,"remaining_time":0.1830096194},
{"learn":[3.307974895],"iteration":823,"passed_time":0.8518170309,"remaining_time":0.1819415017},
{"learn":[3.307321505],"iteration":824,"passed_time":0.8526204468,"remaining_time":0.1808588827},
{"learn":[3.306759087],"iteration":825,"passed_time":0.8533676535,"remaining_time":0.1797650989},
{"learn":[3.30484037],"iteration":826,"passed_time":0.8542020258,"remaining_time":0.1786903875},
{"learn":[3.30201994],"iteration":827,"passed_time":0.8548955407,"remaining_time":0.1775869964},
{"learn":[3.299302297],"iteration":828,"passed_time":0.8555801934,"remaining_time":0.1764827661},
{"learn":[3.298132671],"iteration":829,"passed_time":0.8563140921,"remaining_time":0.1753896333},
{"learn":[3.296976183],"iteration":830,"passed_time":0.8571138399,"remaining_time":0.1743107568},
{"learn":[3.293144745],"iteration":831,"passed_time":0.8580136942,"remaining_time":0.1732527652},
{"learn":[3.290284404],"iteration":832,"passed_time":0.8588087778,"remaining_time":0.1721741487},
{"learn":[3.288285745],"iteration":833,"passed_time":0.8596477125,"remaining_time":0.1711049404},
{"learn":[3.286662667],"iteration":834,"passed_time":0.8603898231,"remaining_time":0.1700171507},
{"learn":[3.285692682],"iteration":835,"passed_time":0.8614324453,"remaining_time":0.16898914},
{"learn":[3.284565611],"iteration":836,"passed_time":0.8622312563,"remaining_time":0.1679136138},
{"learn":[3.283897383],"iteration":837,"passed_time":0.8630875986,"remaining_time":0.1668498699},
{"learn":[3.280712855],"iteration":838,"passed_time":0.8640353328,"remaining_time":0.165804158},
{"learn":[3.280468341],"iteration":839,"passed_time":0.8648487903,"remaining_time":0.1647331029},
{"learn":[3.277814895],"iteration":840,"passed_time":0.8657010088,"remaining_time":0.1636699886},
{"learn":[3.276316385],"iteration":841,"passed_time":0.8665142203,"remaining_time":0.1626000556},
{"learn":[3.27557063],"iteration":842,"passed_time":0.8673748434,"remaining_time":0.1615395616},
{"learn":[3.27499628],"iteration":843,"passed_time":0.868278807,"remaining_time":0.160487552},
{"learn":[3.273569958],"iteration":844,"passed_time":0.8693479337,"remaining_time":0.159466189},
{"learn":[3.269665595],"iteration":845,"passed_time":0.8701630099,"remaining_time":0.1583984675},
{"learn":[3.267984685],"iteration":846,"passed_time":0.8711782384,"remaining_time":0.1573674976},
{"learn":[3.267702508],"iteration":847,"passed_time":0.8719004634,"remaining_time":0.1562840453},
{"learn":[3.266671924],"iteration":848,"passed_time":0.8725852469,"remaining_time":0.1551947848},
{"learn":[3.265359825],"iteration":849,"passed_time":0.8732244954,"remaining_time":0.1540984404},
{"learn":[3.2618983],"iteration":850,"passed_time":0.8739169707,"remaining_time":0.1530124896},
{"learn":[3.260456253],"iteration":851,"passed_time":0.8745470392,"remaining_time":0.1519166218},
{"learn":[3.258389147],"iteration":852,"passed_time":0.8751183251,"remaining_time":0.150811716},
{"learn":[3.258108469],"iteration":853,"passed_time":0.8757467906,"remaining_time":0.1497178354},
{"learn":[3.256424936],"iteration":854,"passed_time":0.8764330918,"remaining_time":0.1486348518},
{"learn":[3.254817983],"iteration":855,"passed_time":0.8770817879,"remaining_time":0.147546469},
{"learn":[3.253898449],"iteration":856,"passed_time":0.8776370799,"remaining_time":0.1464435268},
{"learn":[3.253023652],"iteration":857,"passed_time":0.8782242375,"remaining_time":0.1453471349},
{"learn":[3.252845542],"iteration":858,"passed_time":0.8788200698,"remaining_time":0.1442533525},
{"learn":[3.252316026],"iteration":859,"passed_time":0.8793623675,"remaining_time":0.1431520133},
{"learn":[3.24975301],"iteration":860,"passed_time":0.8798845055,"remaining_time":0.1420487181},
{"learn":[3.249151075],"iteration":861,"passed_time":0.8804297425,"remaining_time":0.1409504692},
{"learn":[3.246257135],"iteration":862,"passed_time":0.8810153186,"remaining_time":0.1398599057},
{"learn":[3.243826471],"iteration":863,"passed_time":0.8815781817,"remaining_time":0.138766936},
{"learn":[3.243190653],"iteration":864,"passed_time":0.8821652867,"remaining_time":0.1376789754},
{"learn":[3.24008797],"iteration":865,"passed_time":0.8828225171,"remaining_time":0.1366030223},
{"learn":[3.240036811],"iteration":866,"passed_time":0.8834004856,"remaining_time":0.1355158761},
{"learn":[3.238676314],"iteration":867,"passed_time":0.8840722026,"remaining_time":0.1344441598},
{"learn":[3.237848782],"iteration":868,"passed_time":0.8848504886,"remaining_time":0.1333894292},
{"learn":[3.236405498],"iteration":869,"passed_time":0.8855252854,"remaining_time":0.1323198702},
{"learn":[3.233378068],"iteration":870,"passed_time":0.8862136532,"remaining_time":0.1312532276},
{"learn":[3.233169169],"iteration":871,"passed_time":0.8867826377,"remaining_time":0.1301699285},
{"learn":[3.232434885],"iteration":872,"passed_time":0.8873835407,"remaining_time":0.1290924509},
{"learn":[3.229978115],"iteration":873,"passed_time":0.8879857371,"remaining_time":0.1280162504},
{"learn":[3.229648848],"iteration":874,"passed_time":0.8885920514,"remaining_time":0.1269417216},
{"learn":[3.227208761],"iteration":875,"passed_time":0.8892173607,"remaining_time":0.1258709506},
{"learn":[3.226258869],"iteration":876,"passed_time":0.8897805047,"remaining_time":0.1247924767},
{"learn":[3.225331995],"iteration":877,"passed_time":0.8905268559,"remaining_time":0.1237406337},
{"learn":[3.221968268],"iteration":878,"passed_time":0.8912221061,"remaining_time":0.1226824515},
{"learn":[3.221166317],"iteration":879,"passed_time":0.8918950557,"remaining_time":0.1216220531},
{"learn":[3.220047503],"iteration":880,"passed_time":0.892576028,"remaining_time":0.1205636179},
{"learn":[3.21982781],"iteration":881,"passed_time":0.8931665768,"remaining_time":0.1194939411},
{"learn":[3.216693405],"iteration":882,"passed_time":0.8938008556,"remaining_time":0.118431144},
{"learn":[3.214798761],"iteration":883,"passed_time":0.894417011,"remaining_time":0.1173669381},
{"learn":[3.214395085],"iteration":884,"passed_time":0.8949683204,"remaining_time":0.1162953185},
{"learn":[3.213470696],"iteration":885,"passed_time":0.8955497201,"remaining_time":0.115228745},
{"learn":[3.211595017],"iteration":886,"passed_time":0.8961152027,"remaining_time":0.1141612378},
{"learn":[3.210965255],"iteration":887,"passed_time":0.8966933934,"remaining_time":0.113096464},
{"learn":[3.209413583],"iteration":888,"passed_time":0.8973054338,"remaining_time":0.1120370114},
{"learn":[3.208331683],"iteration":889,"passed_time":0.8979244383,"remaining_time":0.110979425},
{"learn":[3.207110711],"iteration":890,"passed_time":0.8985829024,"remaining_time":0.1099276502},
{"learn":[3.204519413],"iteration":891,"passed_time":0.8992091813,"remaining_time":0.1088728605},
{"learn":[3.201421296],"iteration":892,"passed_time":0.899827208,"remaining_time":0.1078180417},
{"learn":[3.200691259],"iteration":893,"passed_time":0.9004798756,"remaining_time":0.1067683074},
{"learn":[3.200485067],"iteration":894,"passed_time":0.9010830799,"remaining_time":0.1057136574},
{"learn":[3.197467568],"iteration":895,"passed_time":0.9016622193,"remaining_time":0.1046572219},
{"learn":[3.195838544],"iteration":896,"passed_time":0.9022571916,"remaining_time":0.1036036686},
{"learn":[3.195671746],"iteration":897,"passed_time":0.902812339,"remaining_time":0.1025466131},
{"learn":[3.194213094],"iteration":898,"passed_time":0.9033856326,"remaining_time":0.1014927129},
{"learn":[3.192884691],"iteration":899,"passed_time":0.9040053782,"remaining_time":0.100445042},
{"learn":[3.188364239],"iteration":900,"passed_time":0.9046387907,"remaining_time":0.09939982273},
{"learn":[3.185219478],"iteration":901,"passed_time":0.9051933434,"remaining_time":0.09834694862},
{"learn":[3.184120387],"iteration":902,"passed_time":0.9057432785,"remaining_time":0.09729468219},
{"learn":[3.183725321],"iteration":903,"passed_time":0.90628575,"remaining_time":0.09624273451},
{"learn":[3.181264554],"iteration":904,"passed_time":0.9068448536,"remaining_time":0.09519365866},
{"learn":[3.180741589],"iteration":905,"passed_time":0.907407107,"remaining_time":0.09414599123},
{"learn":[3.179782639],"iteration":906,"passed_time":0.9079460616,"remaining_time":0.09309700521},
{"learn":[3.176377564],"iteration":907,"passed_time":0.9085497932,"remaining_time":0.09205570592},
{"learn":[3.174078182],"iteration":908,"passed_time":0.9091375745,"remaining_time":0.09101377259},
{"learn":[3.171242379],"iteration":909,"passed_time":0.9097058488,"remaining_time":0.08997090813},
{"learn":[3.170421012],"iteration":910,"passed_time":0.9102490044,"remaining_time":0.0889266316},
{"learn":[3.170087224],"iteration":911,"passed_time":0.9108065307,"remaining_time":0.08788484068},
{"learn":[3.167303059],"iteration":912,"passed_time":0.9113739495,"remaining_time":0.08684505323},
{"learn":[3.16705966],"iteration":913,"passed_time":0.9119301007,"remaining_time":0.08580523924},
{"learn":[3.165667683],"iteration":914,"passed_time":0.9125604234,"remaining_time":0.08477337266},
{"learn":[3.164689733],"iteration":915,"passed_time":0.9131124862,"remaining_time":0.08373520616},
{"learn":[3.163311455],"iteration":916,"passed_time":0.9137936333,"remaining_time":0.0827097836},
{"learn":[3.159425016],"iteration":917,"passed_time":0.9144587939,"remaining_time":0.08168368311},
{"learn":[3.159327058],"iteration":918,"passed_time":0.9150608546,"remaining_time":0.08065280656},
{"learn":[3.15819426],"iteration":919,"passed_time":0.9156589816,"remaining_time":0.07962252014},
{"learn":[3.157086603],"iteration":920,"passed_time":0.9162074776,"remaining_time":0.07858891502},
{"learn":[3.153354154],"iteration":921,"passed_time":0.9167484466,"remaining_time":0.07755572542},
{"learn":[3.153261317],"iteration":922,"passed_time":0.9172685947,"remaining_time":0.07652186543},
{"learn":[3.153168454],"iteration":923,"passed_time":0.917794014,"remaining_time":0.07548955093},
{"learn":[3.152080399],"iteration":924,"passed_time":0.9184075975,"remaining_time":0.07446548088},
{"learn":[3.151635144],"iteration":925,"passed_time":0.9191443605,"remaining_time":0.07345214112},
{"learn":[3.147762655],"iteration":926,"passed_time":0.9197767431,"remaining_time":0.07243117826},
{"learn":[3.147172317],"iteration":927,"passed_time":0.9203878437,"remaining_time":0.07140940167},
{"learn":[3.146254125],"iteration":928,"passed_time":0.9209551418,"remaining_time":0.07038516154},
{"learn":[3.144869828],"iteration":929,"passed_time":0.9215562516,"remaining_time":0.06936444904},
{"learn":[3.143466218],"iteration":930,"passed_time":0.9220980016,"remaining_time":0.06834023857},
{"learn":[3.141919643],"iteration":931,"passed_time":0.922619749,"remaining_time":0.06731560401},
{"learn":[3.141054135],"iteration":932,"passed_time":0.9232301644,"remaining_time":0.06629841481},
{"learn":[3.139390417],"iteration":933,"passed_time":0.923780663,"remaining_time":0.06527786269},
{"learn":[3.139025283],"iteration":934,"passed_time":0.9243412612,"remaining_time":0.06425901816},
{"learn":[3.137824183],"iteration":935,"passed_time":0.9249292702,"remaining_time":0.06324302702},
{"learn":[3.135620453],"iteration":936,"passed_time":0.9255473834,"remaining_time":0.06222997348},
{"learn":[3.13443178],"iteration":937,"passed_time":0.926141392,"remaining_time":0.06121616877},
{"learn":[3.132765713],"iteration":938,"passed_time":0.926682121,"remaining_time":0.060199797},
{"learn":[3.131434124],"iteration":939,"passed_time":0.9272413853,"remaining_time":0.05918562034},
{"learn":[3.128384262],"iteration":940,"passed_time":0.9278200108,"remaining_time":0.05817362448},
{"learn":[3.128120455],"iteration":941,"passed_time":0.928392463,"remaining_time":0.05716216863},
{"learn":[3.126314615],"iteration":942,"passed_time":0.9289885122,"remaining_time":0.05615307019},
{"learn":[3.125409666],"iteration":943,"passed_time":0.9296384726,"remaining_time":0.05514804498},
{"learn":[3.123072589],"iteration":944,"passed_time":0.9302654211,"remaining_time":0.05414243192},
{"learn":[3.122921099],"iteration":945,"passed_time":0.9309976661,"remaining_time":0.05314362999},
{"learn":[3.122182662],"iteration":946,"passed_time":0.9316208656,"remaining_time":0.05213928815},
{"learn":[3.120040951],"iteration":947,"passed_time":0.9322157462,"remaining_time":0.05113419705},
{"learn":[3.118767799],"iteration":948,"passed_time":0.932848871,"remaining_time":0.05013202573},
{"learn":[3.118203218],"iteration":949,"passed_time":0.9334814074,"remaining_time":0.04913060039},
{"learn":[3.116343362],"iteration":950,"passed_time":0.9342073903,"remaining_time":0.04813476564},
{"learn":[3.11480829],"iteration":951,"passed_time":0.9348647131,"remaining_time":0.04713603596},
{"learn":[3.112607903],"iteration":952,"passed_time":0.9354394078,"remaining_time":0.04613394771},
{"learn":[3.111661241],"iteration":953,"passed_time":0.9360614201,"remaining_time":0.04513503703},
{"learn":[3.110249676],"iteration":954,"passed_time":0.9366996674,"remaining_time":0.04413768066},
{"learn":[3.107333579],"iteration":955,"passed_time":0.937355768,"remaining_time":0.04314189727},
{"learn":[3.107149851],"iteration":956,"passed_time":0.9379950087,"remaining_time":0.04214606622},
{"learn":[3.106867336],"iteration":957,"passed_time":0.9385983755,"remaining_time":0.04114940686},
{"learn":[3.10364681],"iteration":958,"passed_time":0.9392130404,"remaining_time":0.04015405073},
{"learn":[3.102703811],"iteration":959,"passed_time":0.9397664335,"remaining_time":0.03915693473},
{"learn":[3.101469264],"iteration":960,"passed_time":0.94031783,"remaining_time":0.03816066116},
{"learn":[3.09863569],"iteration":961,"passed_time":0.9408683979,"remaining_time":0.03716527975},
{"learn":[3.09645939],"iteration":962,"passed_time":0.9414192273,"remaining_time":0.0361708322},
{"learn":[3.096240186],"iteration":963,"passed_time":0.9419551018,"remaining_time":0.03517674654},
{"learn":[3.094838828],"iteration":964,"passed_time":0.9425989627,"remaining_time":0.03418752714},
{"learn":[3.094176802],"iteration":965,"passed_time":0.9433587418,"remaining_time":0.03320310271},
{"learn":[3.093182279],"iteration":966,"passed_time":0.9439672389,"remaining_time":0.03221398023},
{"learn":[3.090150687],"iteration":967,"passed_time":0.9446303199,"remaining_time":0.03122744859},
{"learn":[3.088612829],"iteration":968,"passed_time":0.9453040096,"remaining_time":0.03024192394},
{"learn":[3.087153684],"iteration":969,"passed_time":0.9459557716,"remaining_time":0.02925636407},
{"learn":[3.085866843],"iteration":970,"passed_time":0.9465714053,"remaining_time":0.02827041272},
{"learn":[3.082669094],"iteration":971,"passed_time":0.9471668538,"remaining_time":0.02728464188},
{"learn":[3.081047548],"iteration":972,"passed_time":0.9477730064,"remaining_time":0.02629997037},
{"learn":[3.079684322],"iteration":973,"passed_time":0.9484310439,"remaining_time":0.02531746113},
{"learn":[3.07613431],"iteration":974,"passed_time":0.9490644139,"remaining_time":0.02433498497},
{"learn":[3.074005935],"iteration":975,"passed_time":0.9496590918,"remaining_time":0.02335227275},
{"learn":[3.072988853],"iteration":976,"passed_time":0.950231743,"remaining_time":0.02236983632},
{"learn":[3.072344268],"iteration":977,"passed_time":0.950827601,"remaining_time":0.02138875994},
{"learn":[3.070654438],"iteration":978,"passed_time":0.9514300504,"remaining_time":0.02040861191},
{"learn":[3.069724506],"iteration":979,"passed_time":0.9519918671,"remaining_time":0.01942840545},
{"learn":[3.067763166],"iteration":980,"passed_time":0.952576803,"remaining_time":0.01844949975},
{"learn":[3.066737893],"iteration":981,"passed_time":0.953177263,"remaining_time":0.01747168099},
{"learn":[3.065248174],"iteration":982,"passed_time":0.9537610475,"remaining_time":0.01649434162},
{"learn":[3.063186837],"iteration":983,"passed_time":0.9543277196,"remaining_time":0.0155175239},
{"learn":[3.062880371],"iteration":984,"passed_time":0.9548775779,"remaining_time":0.01454128291},
{"learn":[3.061288645],"iteration":985,"passed_time":0.9554159199,"remaining_time":0.01356574328},
{"learn":[3.059970575],"iteration":986,"passed_time":0.9559600324,"remaining_time":0.01259116557},
{"learn":[3.059576341],"iteration":987,"passed_time":0.956489438,"remaining_time":0.01161728062},
{"learn":[3.058175919],"iteration":988,"passed_time":0.9570781539,"remaining_time":0.01064495419},
{"learn":[3.056830702],"iteration":989,"passed_time":0.9576437472,"remaining_time":0.009673169163},
{"learn":[3.056336579],"iteration":990,"passed_time":0.9581839016,"remaining_time":0.00870197287},
{"learn":[3.055810414],"iteration":991,"passed_time":0.9587414812,"remaining_time":0.007731786138},
{"learn":[3.055476518],"iteration":992,"passed_time":0.9593185338,"remaining_time":0.006762567711},
{"learn":[3.053331734],"iteration":993,"passed_time":0.9599557128,"remaining_time":0.005794501284},
{"learn":[3.050890374],"iteration":994,"passed_time":0.9606063708,"remaining_time":0.004827167692},
{"learn":[3.04972623],"iteration":995,"passed_time":0.9612316719,"remaining_time":0.00386036816},
{"learn":[3.047217327],"iteration":996,"passed_time":0.9618574753,"remaining_time":0.002894255191},
{"learn":[3.047155483],"iteration":997,"passed_time":0.9624657183,"remaining_time":0.001928789015},
{"learn":[3.04430671],"iteration":998,"passed_time":0.9631151366,"remaining_time":0.0009640792158},
{"learn":[3.042664195],"iteration":999,"passed_time":0.9636829213,"remaining_time":0}
]}